<email><tf date="2000/01/27 08:44" file="FINDMAIL/HTML_files/1 (17th copy)/25135.txt" id="25135" sender="phillip.allen@enron.com" subject="dopewars">1</tf><tf date="2000/01/27 08:44" file="FINDMAIL/HTML_files/1 (23rd copy)/9538.txt" id="9538" sender="phillip.allen@enron.com" subject="dopewars">1</tf><tf date="2000/01/27 08:44" file="FINDMAIL/HTML_files/1 (copy)/10538.txt" id="10538" sender="phillip.allen@enron.com" subject="dopewars">1</tf><tf date="2000/01/27 08:44" file="FINDMAIL/HTML_files/1 (20th copy)/23538.txt" id="23538" sender="phillip.allen@enron.com" subject="dopewars">1</tf><tf date="2000/01/27 08:44" file="FINDMAIL/HTML_files/1 (6th copy)/16135.txt" id="16135" sender="phillip.allen@enron.com" subject="dopewars">1</tf><tf date="2000/01/27 08:44" file="FINDMAIL/HTML_files/1 (24th copy)/14135.txt" id="14135" sender="phillip.allen@enron.com" subject="dopewars">1</tf><tf date="2000/01/27 08:44" file="FINDMAIL/HTML_files/1 (24th copy)/14538.txt" id="14538" sender="phillip.allen@enron.com" subject="dopewars">1</tf><tf date="2000/01/27 08:44" file="FINDMAIL/HTML_files/1 (27th copy)/15538.txt" id="15538" sender="phillip.allen@enron.com" subject="dopewars">1</tf><tf date="2000/01/27 08:44" file="FINDMAIL/HTML_files/1 (8th copy)/11135.txt" id="11135" sender="phillip.allen@enron.com" subject="dopewars">1</tf><tf date="2000/01/27 08:44" file="FINDMAIL/HTML_files/1 (25th copy)/17538.txt" id="17538" sender="phillip.allen@enron.com" subject="dopewars">1</tf><tf date="2000/01/27 08:44" file="FINDMAIL/HTML_files/1 (28th copy)/135.txt" id="135" sender="phillip.allen@enron.com" subject="dopewars">1</tf><tf date="2000/01/27 08:44" file="FINDMAIL/HTML_files/1 (15th copy)/3538.txt" id="3538" sender="phillip.allen@enron.com" subject="dopewars">1</tf><tf date="2000/01/27 08:44" file="FINDMAIL/HTML_files/1 (10th copy)/8135.txt" id="8135" sender="phillip.allen@enron.com" subject="dopewars">1</tf><tf date="2000/01/27 08:44" file="FINDMAIL/HTML_files/1 (another copy)/5135.txt" id="5135" sender="phillip.allen@enron.com" subject="dopewars">1</tf><tf date="2000/01/27 08:44" file="FINDMAIL/HTML_files/1 (26th copy)/7135.txt" id="7135" sender="phillip.allen@enron.com" subject="dopewars">1</tf><tf date="2000/01/27 08:44" file="FINDMAIL/HTML_files/1 (4th copy)/6538.txt" id="6538" sender="phillip.allen@enron.com" subject="dopewars">1</tf><tf date="2000/01/27 08:44" file="FINDMAIL/HTML_files/1 (12th copy)/18538.txt" id="18538" sender="phillip.allen@enron.com" subject="dopewars">1</tf><tf date="2000/01/27 08:44" file="FINDMAIL/HTML_files/1 (11th copy)/2135.txt" id="2135" sender="phillip.allen@enron.com" subject="dopewars">1</tf><tf date="2000/01/27 08:44" file="FINDMAIL/HTML_files/1 (22nd copy)/4538.txt" id="4538" sender="phillip.allen@enron.com" subject="dopewars">1</tf><tf date="2000/01/27 08:44" file="FINDMAIL/HTML_files/1 (29th copy)/29135.txt" id="29135" sender="phillip.allen@enron.com" subject="dopewars">1</tf><tf date="2000/01/27 08:44" file="FINDMAIL/HTML_files/1 (12th copy)/18135.txt" id="18135" sender="phillip.allen@enron.com" subject="dopewars">1</tf><tf date="2000/01/27 08:44" file="FINDMAIL/HTML_files/1 (16th copy)/22135.txt" id="22135" sender="phillip.allen@enron.com" subject="dopewars">1</tf><tf date="2000/01/27 08:44" file="FINDMAIL/HTML_files/1 (3rd copy)/19135.txt" id="19135" sender="phillip.allen@enron.com" subject="dopewars">1</tf><tf date="2000/01/27 08:44" file="FINDMAIL/HTML_files/1 (19th copy)/27538.txt" id="27538" sender="phillip.allen@enron.com" subject="dopewars">1</tf><tf date="2000/01/27 08:44" file="FINDMAIL/HTML_files/1 (18th copy)/26135.txt" id="26135" sender="phillip.allen@enron.com" subject="dopewars">1</tf><tf date="2000/01/27 08:44" file="FINDMAIL/HTML_files/1 (19th copy)/27135.txt" id="27135" sender="phillip.allen@enron.com" subject="dopewars">1</tf><tf date="2000/01/27 08:44" file="FINDMAIL/HTML_files/1 (26th copy)/7538.txt" id="7538" sender="phillip.allen@enron.com" subject="dopewars">1</tf><tf date="2000/01/27 08:44" file="FINDMAIL/HTML_files/1 (18th copy)/26538.txt" id="26538" sender="phillip.allen@enron.com" subject="dopewars">1</tf><tf date="2000/01/27 08:44" file="FINDMAIL/HTML_files/1/12135.txt" id="12135" sender="phillip.allen@enron.com" subject="dopewars">1</tf><tf date="2000/01/27 08:44" file="FINDMAIL/HTML_files/1 (copy)/10135.txt" id="10135" sender="phillip.allen@enron.com" subject="dopewars">1</tf><tf date="2000/01/27 08:44" file="FINDMAIL/HTML_files/1 (20th copy)/23135.txt" id="23135" sender="phillip.allen@enron.com" subject="dopewars">1</tf><tf date="2000/01/27 08:44" file="FINDMAIL/HTML_files/1 (23rd copy)/9135.txt" id="9135" sender="phillip.allen@enron.com" subject="dopewars">1</tf><tf date="2000/01/27 08:44" file="FINDMAIL/HTML_files/1 (17th copy)/25538.txt" id="25538" sender="phillip.allen@enron.com" subject="dopewars">1</tf><tf date="2000/01/27 08:44" file="FINDMAIL/HTML_files/1 (21st copy)/20135.txt" id="20135" sender="phillip.allen@enron.com" subject="dopewars">1</tf><tf date="2000/01/27 08:44" file="FINDMAIL/HTML_files/1 (6th copy)/16538.txt" id="16538" sender="phillip.allen@enron.com" subject="dopewars">1</tf><tf date="2000/01/27 08:44" file="FINDMAIL/HTML_files/1 (3rd copy)/19538.txt" id="19538" sender="phillip.allen@enron.com" subject="dopewars">1</tf><tf date="2000/01/27 08:44" file="FINDMAIL/HTML_files/1 (7th copy)/21135.txt" id="21135" sender="phillip.allen@enron.com" subject="dopewars">1</tf><tf date="2000/01/27 08:44" file="FINDMAIL/HTML_files/1 (5th copy)/1135.txt" id="1135" sender="phillip.allen@enron.com" subject="dopewars">1</tf><tf date="2000/01/27 08:44" file="FINDMAIL/HTML_files/1 (21st copy)/20538.txt" id="20538" sender="phillip.allen@enron.com" subject="dopewars">1</tf><tf date="2000/01/27 08:44" file="FINDMAIL/HTML_files/1 (10th copy)/8538.txt" id="8538" sender="phillip.allen@enron.com" subject="dopewars">1</tf><tf date="2000/01/27 08:44" file="FINDMAIL/HTML_files/1 (13th copy)/24135.txt" id="24135" sender="phillip.allen@enron.com" subject="dopewars">1</tf><tf date="2000/01/27 08:44" file="FINDMAIL/HTML_files/1 (13th copy)/24538.txt" id="24538" sender="phillip.allen@enron.com" subject="dopewars">1</tf><tf date="2000/01/27 08:44" file="FINDMAIL/HTML_files/1 (16th copy)/22538.txt" id="22538" sender="phillip.allen@enron.com" subject="dopewars">1</tf><tf date="2000/01/27 08:44" file="FINDMAIL/HTML_files/1 (9th copy)/28538.txt" id="28538" sender="phillip.allen@enron.com" subject="dopewars">1</tf><tf date="2000/01/27 08:44" file="FINDMAIL/HTML_files/1 (14th copy)/13538.txt" id="13538" sender="phillip.allen@enron.com" subject="dopewars">1</tf><tf date="2000/01/27 08:44" file="FINDMAIL/HTML_files/1 (another copy)/5538.txt" id="5538" sender="phillip.allen@enron.com" subject="dopewars">1</tf><tf date="2000/01/27 08:44" file="FINDMAIL/HTML_files/1 (25th copy)/17135.txt" id="17135" sender="phillip.allen@enron.com" subject="dopewars">1</tf><tf date="2000/01/27 08:44" file="FINDMAIL/HTML_files/1 (27th copy)/15135.txt" id="15135" sender="phillip.allen@enron.com" subject="dopewars">1</tf><tf date="2000/01/27 08:44" file="FINDMAIL/HTML_files/1 (15th copy)/3135.txt" id="3135" sender="phillip.allen@enron.com" subject="dopewars">1</tf><tf date="2000/01/27 08:44" file="FINDMAIL/HTML_files/1 (8th copy)/11538.txt" id="11538" sender="phillip.allen@enron.com" subject="dopewars">1</tf><tf date="2000/01/27 08:44" file="FINDMAIL/HTML_files/1 (7th copy)/21538.txt" id="21538" sender="phillip.allen@enron.com" subject="dopewars">1</tf><tf date="2000/01/27 08:44" file="FINDMAIL/HTML_files/1 (29th copy)/29538.txt" id="29538" sender="phillip.allen@enron.com" subject="dopewars">1</tf><tf date="2000/01/27 08:44" file="FINDMAIL/HTML_files/1 (22nd copy)/4135.txt" id="4135" sender="phillip.allen@enron.com" subject="dopewars">1</tf><tf date="2000/01/27 08:44" file="FINDMAIL/HTML_files/1/12538.txt" id="12538" sender="phillip.allen@enron.com" subject="dopewars">1</tf><tf date="2000/01/27 08:44" file="FINDMAIL/HTML_files/1 (4th copy)/6135.txt" id="6135" sender="phillip.allen@enron.com" subject="dopewars">1</tf><tf date="2000/01/27 08:44" file="FINDMAIL/HTML_files/1 (14th copy)/13135.txt" id="13135" sender="phillip.allen@enron.com" subject="dopewars">1</tf><tf date="2000/01/27 08:44" file="FINDMAIL/HTML_files/1 (11th copy)/2538.txt" id="2538" sender="phillip.allen@enron.com" subject="dopewars">1</tf><tf date="2000/01/27 08:44" file="FINDMAIL/HTML_files/1 (9th copy)/28135.txt" id="28135" sender="phillip.allen@enron.com" subject="dopewars">1</tf><tf date="2000/01/27 08:44" file="FINDMAIL/HTML_files/1 (5th copy)/1538.txt" id="1538" sender="phillip.allen@enron.com" subject="dopewars">1</tf><tf date="2000/01/27 08:44" file="FINDMAIL/HTML_files/1 (28th copy)/538.txt" id="538" sender="phillip.allen@enron.com" subject="dopewars">1</tf></email>