<email><tf date="2001/04/04 07:43" file="FINDMAIL/HTML_files/1 (24th copy)/14853.txt" id="14853" sender="phillip.allen@enron.com" subject="Re Answers to List">1</tf><tf date="2000/03/13 05:31" file="FINDMAIL/HTML_files/1 (24th copy)/14851.txt" id="14851" sender="phillip.allen@enron.com" subject="Priority List">1</tf><tf date="2001/04/04 07:43" file="FINDMAIL/HTML_files/1 (5th copy)/1853.txt" id="1853" sender="phillip.allen@enron.com" subject="Re Answers to List">1</tf><tf date="2001/04/18 01:11" file="FINDMAIL/HTML_files/1 (copy)/10298.txt" id="10298" sender="phillip.allen@enron.com" subject="approved trader list">1</tf><tf date="2000/09/12 04:23" file="FINDMAIL/HTML_files/1 (8th copy)/11988.txt" id="11988" sender="phillip.allen@enron.com" subject="Contact list for mid market">1</tf><tf date="2001/04/18 11:11" file="FINDMAIL/HTML_files/1 (copy)/10512.txt" id="10512" sender="phillip.allen@enron.com" subject="approved trader list">1</tf><tf date="2000/03/13 05:31" file="FINDMAIL/HTML_files/1 (copy)/10459.txt" id="10459" sender="phillip.allen@enron.com" subject="Priority List">1</tf><tf date="2000/03/13 05:31" file="FINDMAIL/HTML_files/1 (9th copy)/28851.txt" id="28851" sender="phillip.allen@enron.com" subject="Priority List">1</tf><tf date="2001/04/04 07:43" file="FINDMAIL/HTML_files/1 (9th copy)/28853.txt" id="28853" sender="phillip.allen@enron.com" subject="Re Answers to List">1</tf><tf date="2000/09/12 04:23" file="FINDMAIL/HTML_files/1 (another copy)/5988.txt" id="5988" sender="phillip.allen@enron.com" subject="Contact list for mid market">1</tf><tf date="2000/10/09 07:16" file="FINDMAIL/HTML_files/1/12526.txt" id="12526" sender="phillip.allen@enron.com" subject="Consolidated positions Issues To Do list">1</tf><tf date="2001/03/26 02:03" file="FINDMAIL/HTML_files/1 (7th copy)/21762.txt" id="21762" sender="phillip.allen@enron.com" subject="Current Gas Desk List">1</tf><tf date="2000/09/12 04:23" file="FINDMAIL/HTML_files/1 (24th copy)/14988.txt" id="14988" sender="phillip.allen@enron.com" subject="Contact list for mid market">1</tf><tf date="2000/03/13 05:31" file="FINDMAIL/HTML_files/1 (3rd copy)/19395.txt" id="19395" sender="phillip.allen@enron.com" subject="Priority List">1</tf><tf date="2000/10/09 07:00" file="FINDMAIL/HTML_files/1 (copy)/10583.txt" id="10583" sender="phillip.allen@enron.com" subject="Consolidated positions Issues To Do list">1</tf><tf date="2001/04/04 07:43" file="FINDMAIL/HTML_files/1 (15th copy)/3853.txt" id="3853" sender="phillip.allen@enron.com" subject="Re Answers to List">1</tf><tf date="2000/03/13 05:31" file="FINDMAIL/HTML_files/1 (15th copy)/3851.txt" id="3851" sender="phillip.allen@enron.com" subject="Priority List">1</tf><tf date="2000/09/12 04:23" file="FINDMAIL/HTML_files/1 (10th copy)/8905.txt" id="8905" sender="phillip.allen@enron.com" subject="Contact list for mid market">1</tf><tf date="2000/03/13 05:31" file="FINDMAIL/HTML_files/1 (8th copy)/11851.txt" id="11851" sender="phillip.allen@enron.com" subject="Priority List">1</tf><tf date="2000/10/09 07:00" file="FINDMAIL/HTML_files/1 (16th copy)/22182.txt" id="22182" sender="phillip.allen@enron.com" subject="Consolidated positions Issues To Do list">1</tf><tf date="2001/04/04 07:43" file="FINDMAIL/HTML_files/1 (8th copy)/11853.txt" id="11853" sender="phillip.allen@enron.com" subject="Re Answers to List">1</tf><tf date="1979/12/31 16:00" file="FINDMAIL/HTML_files/1 (23rd copy)/9934.txt" id="9934" sender="phillip.allen@enron.com" subject="systems wish list">1</tf><tf date="2000/10/09 07:00" file="FINDMAIL/HTML_files/1 (8th copy)/11182.txt" id="11182" sender="phillip.allen@enron.com" subject="Consolidated positions Issues To Do list">1</tf><tf date="2000/03/13 05:32" file="FINDMAIL/HTML_files/1 (13th copy)/24155.txt" id="24155" sender="phillip.allen@enron.com" subject="Priority List">1</tf><tf date="2001/03/26 02:03" file="FINDMAIL/HTML_files/1 (16th copy)/22762.txt" id="22762" sender="phillip.allen@enron.com" subject="Current Gas Desk List">1</tf><tf date="1979/12/31 16:00" file="FINDMAIL/HTML_files/1/12934.txt" id="12934" sender="phillip.allen@enron.com" subject="systems wish list">1</tf><tf date="2000/03/13 05:31" file="FINDMAIL/HTML_files/1 (11th copy)/2851.txt" id="2851" sender="phillip.allen@enron.com" subject="Priority List">1</tf><tf date="2001/04/04 07:43" file="FINDMAIL/HTML_files/1 (11th copy)/2853.txt" id="2853" sender="phillip.allen@enron.com" subject="Re Answers to List">1</tf><tf date="2000/10/09 07:16" file="FINDMAIL/HTML_files/1 (9th copy)/28484.txt" id="28484" sender="phillip.allen@enron.com" subject="Consolidated positions Issues To Do list">1</tf><tf date="1979/12/31 16:00" file="FINDMAIL/HTML_files/1 (3rd copy)/19271.txt" id="19271" sender="phillip.allen@enron.com" subject="systems wish list">1</tf><tf date="2000/03/13 05:32" file="FINDMAIL/HTML_files/1 (4th copy)/6155.txt" id="6155" sender="phillip.allen@enron.com" subject="Priority List">1</tf><tf date="2000/10/09 07:16" file="FINDMAIL/HTML_files/1/12708.txt" id="12708" sender="phillip.allen@enron.com" subject="Consolidated positions Issues To Do list">1</tf><tf date="2000/03/13 05:31" file="FINDMAIL/HTML_files/1 (29th copy)/29459.txt" id="29459" sender="phillip.allen@enron.com" subject="Priority List">1</tf><tf date="2000/10/09 07:16" file="FINDMAIL/HTML_files/1 (5th copy)/1708.txt" id="1708" sender="phillip.allen@enron.com" subject="Consolidated positions Issues To Do list">1</tf><tf date="2000/10/09 07:00" file="FINDMAIL/HTML_files/1 (24th copy)/14182.txt" id="14182" sender="phillip.allen@enron.com" subject="Consolidated positions Issues To Do list">1</tf><tf date="2000/09/12 04:23" file="FINDMAIL/HTML_files/1 (copy)/10199.txt" id="10199" sender="phillip.allen@enron.com" subject="Contact list for mid market">1</tf><tf date="2000/03/13 05:31" file="FINDMAIL/HTML_files/1 (another copy)/5851.txt" id="5851" sender="phillip.allen@enron.com" subject="Priority List">1</tf><tf date="2001/04/18 01:11" file="FINDMAIL/HTML_files/1 (28th copy)/298.txt" id="298" sender="phillip.allen@enron.com" subject="approved trader list">1</tf><tf date="2001/04/04 07:43" file="FINDMAIL/HTML_files/1 (27th copy)/15853.txt" id="15853" sender="phillip.allen@enron.com" subject="Re Answers to List">1</tf><tf date="1979/12/31 16:00" file="FINDMAIL/HTML_files/1 (19th copy)/27271.txt" id="27271" sender="phillip.allen@enron.com" subject="systems wish list">1</tf><tf date="2000/03/13 05:32" file="FINDMAIL/HTML_files/1 (25th copy)/17155.txt" id="17155" sender="phillip.allen@enron.com" subject="Priority List">1</tf><tf date="2000/03/13 05:31" file="FINDMAIL/HTML_files/1 (12th copy)/18395.txt" id="18395" sender="phillip.allen@enron.com" subject="Priority List">1</tf><tf date="2000/10/09 07:16" file="FINDMAIL/HTML_files/1 (17th copy)/25526.txt" id="25526" sender="phillip.allen@enron.com" subject="Consolidated positions Issues To Do list">1</tf><tf date="2000/09/12 04:23" file="FINDMAIL/HTML_files/1 (28th copy)/199.txt" id="199" sender="phillip.allen@enron.com" subject="Contact list for mid market">1</tf><tf date="2000/09/12 04:23" file="FINDMAIL/HTML_files/1 (4th copy)/6988.txt" id="6988" sender="phillip.allen@enron.com" subject="Contact list for mid market">1</tf><tf date="1979/12/31 16:00" file="FINDMAIL/HTML_files/1 (28th copy)/271.txt" id="271" sender="phillip.allen@enron.com" subject="systems wish list">1</tf><tf date="2000/10/09 07:16" file="FINDMAIL/HTML_files/1 (6th copy)/16708.txt" id="16708" sender="phillip.allen@enron.com" subject="Consolidated positions Issues To Do list">1</tf><tf date="2000/03/13 05:31" file="FINDMAIL/HTML_files/1 (24th copy)/14459.txt" id="14459" sender="phillip.allen@enron.com" subject="Priority List">1</tf><tf date="2000/09/12 04:23" file="FINDMAIL/HTML_files/1/12988.txt" id="12988" sender="phillip.allen@enron.com" subject="Contact list for mid market">1</tf><tf date="2001/04/18 11:11" file="FINDMAIL/HTML_files/1 (12th copy)/18512.txt" id="18512" sender="phillip.allen@enron.com" subject="approved trader list">1</tf><tf date="2000/03/13 05:32" file="FINDMAIL/HTML_files/1 (18th copy)/26155.txt" id="26155" sender="phillip.allen@enron.com" subject="Priority List">1</tf><tf date="2000/09/12 04:23" file="FINDMAIL/HTML_files/1 (11th copy)/2988.txt" id="2988" sender="phillip.allen@enron.com" subject="Contact list for mid market">1</tf><tf date="2000/09/12 04:23" file="FINDMAIL/HTML_files/1 (25th copy)/17988.txt" id="17988" sender="phillip.allen@enron.com" subject="Contact list for mid market">1</tf><tf date="2000/03/13 05:31" file="FINDMAIL/HTML_files/1 (18th copy)/26395.txt" id="26395" sender="phillip.allen@enron.com" subject="Priority List">1</tf><tf date="2000/10/09 07:00" file="FINDMAIL/HTML_files/1 (27th copy)/15583.txt" id="15583" sender="phillip.allen@enron.com" subject="Consolidated positions Issues To Do list">1</tf><tf date="2000/10/09 07:16" file="FINDMAIL/HTML_files/1 (28th copy)/526.txt" id="526" sender="phillip.allen@enron.com" subject="Consolidated positions Issues To Do list">1</tf><tf date="2000/09/12 04:23" file="FINDMAIL/HTML_files/1 (13th copy)/24905.txt" id="24905" sender="phillip.allen@enron.com" subject="Contact list for mid market">1</tf><tf date="2001/03/26 02:03" file="FINDMAIL/HTML_files/1 (8th copy)/11762.txt" id="11762" sender="phillip.allen@enron.com" subject="Current Gas Desk List">1</tf><tf date="2000/10/09 07:16" file="FINDMAIL/HTML_files/1 (29th copy)/29526.txt" id="29526" sender="phillip.allen@enron.com" subject="Consolidated positions Issues To Do list">1</tf><tf date="2000/03/13 05:32" file="FINDMAIL/HTML_files/1 (23rd copy)/9155.txt" id="9155" sender="phillip.allen@enron.com" subject="Priority List">1</tf><tf date="2000/09/12 04:23" file="FINDMAIL/HTML_files/1 (14th copy)/13905.txt" id="13905" sender="phillip.allen@enron.com" subject="Contact list for mid market">1</tf><tf date="2000/10/09 07:00" file="FINDMAIL/HTML_files/1 (15th copy)/3583.txt" id="3583" sender="phillip.allen@enron.com" subject="Consolidated positions Issues To Do list">1</tf><tf date="2001/04/18 11:11" file="FINDMAIL/HTML_files/1 (10th copy)/8512.txt" id="8512" sender="phillip.allen@enron.com" subject="approved trader list">1</tf><tf date="2000/03/13 05:31" file="FINDMAIL/HTML_files/1 (9th copy)/28395.txt" id="28395" sender="phillip.allen@enron.com" subject="Priority List">1</tf><tf date="2000/09/12 04:23" file="FINDMAIL/HTML_files/1 (22nd copy)/4199.txt" id="4199" sender="phillip.allen@enron.com" subject="Contact list for mid market">1</tf><tf date="2001/03/26 02:03" file="FINDMAIL/HTML_files/1 (11th copy)/2762.txt" id="2762" sender="phillip.allen@enron.com" subject="Current Gas Desk List">1</tf><tf date="2000/10/09 07:16" file="FINDMAIL/HTML_files/1 (23rd copy)/9526.txt" id="9526" sender="phillip.allen@enron.com" subject="Consolidated positions Issues To Do list">1</tf><tf date="2000/10/09 07:16" file="FINDMAIL/HTML_files/1 (18th copy)/26708.txt" id="26708" sender="phillip.allen@enron.com" subject="Consolidated positions Issues To Do list">1</tf><tf date="1979/12/31 16:00" file="FINDMAIL/HTML_files/1 (4th copy)/6934.txt" id="6934" sender="phillip.allen@enron.com" subject="systems wish list">1</tf><tf date="2000/10/09 07:00" file="FINDMAIL/HTML_files/1 (12th copy)/18182.txt" id="18182" sender="phillip.allen@enron.com" subject="Consolidated positions Issues To Do list">1</tf><tf date="2000/09/12 04:23" file="FINDMAIL/HTML_files/1 (26th copy)/7905.txt" id="7905" sender="phillip.allen@enron.com" subject="Contact list for mid market">1</tf><tf date="2000/10/09 07:16" file="FINDMAIL/HTML_files/1 (23rd copy)/9484.txt" id="9484" sender="phillip.allen@enron.com" subject="Consolidated positions Issues To Do list">1</tf><tf date="1979/12/31 16:00" file="FINDMAIL/HTML_files/1 (4th copy)/6271.txt" id="6271" sender="phillip.allen@enron.com" subject="systems wish list">1</tf><tf date="2000/09/12 04:23" file="FINDMAIL/HTML_files/1 (7th copy)/21199.txt" id="21199" sender="phillip.allen@enron.com" subject="Contact list for mid market">1</tf><tf date="2000/10/09 07:16" file="FINDMAIL/HTML_files/1 (24th copy)/14526.txt" id="14526" sender="phillip.allen@enron.com" subject="Consolidated positions Issues To Do list">1</tf><tf date="2000/09/12 04:23" file="FINDMAIL/HTML_files/1 (28th copy)/905.txt" id="905" sender="phillip.allen@enron.com" subject="Contact list for mid market">1</tf><tf date="2000/10/09 07:16" file="FINDMAIL/HTML_files/1 (26th copy)/7708.txt" id="7708" sender="phillip.allen@enron.com" subject="Consolidated positions Issues To Do list">1</tf><tf date="2000/03/13 05:31" file="FINDMAIL/HTML_files/1 (5th copy)/1459.txt" id="1459" sender="phillip.allen@enron.com" subject="Priority List">1</tf><tf date="2001/04/18 01:11" file="FINDMAIL/HTML_files/1 (7th copy)/21298.txt" id="21298" sender="phillip.allen@enron.com" subject="approved trader list">1</tf><tf date="2000/10/09 07:00" file="FINDMAIL/HTML_files/1 (28th copy)/432.txt" id="432" sender="phillip.allen@enron.com" subject="Consolidated positions Issues To Do list">1</tf><tf date="2000/03/13 05:31" file="FINDMAIL/HTML_files/1 (12th copy)/18459.txt" id="18459" sender="phillip.allen@enron.com" subject="Priority List">1</tf><tf date="2000/10/09 07:16" file="FINDMAIL/HTML_files/1 (21st copy)/20526.txt" id="20526" sender="phillip.allen@enron.com" subject="Consolidated positions Issues To Do list">1</tf><tf date="2000/10/09 07:00" file="FINDMAIL/HTML_files/1 (3rd copy)/19182.txt" id="19182" sender="phillip.allen@enron.com" subject="Consolidated positions Issues To Do list">1</tf><tf date="2000/10/09 07:16" file="FINDMAIL/HTML_files/1 (20th copy)/23484.txt" id="23484" sender="phillip.allen@enron.com" subject="Consolidated positions Issues To Do list">1</tf><tf date="2000/10/09 07:16" file="FINDMAIL/HTML_files/1 (21st copy)/20484.txt" id="20484" sender="phillip.allen@enron.com" subject="Consolidated positions Issues To Do list">1</tf><tf date="2001/04/18 01:11" file="FINDMAIL/HTML_files/1 (15th copy)/3298.txt" id="3298" sender="phillip.allen@enron.com" subject="approved trader list">1</tf><tf date="2000/10/09 07:00" file="FINDMAIL/HTML_files/1 (18th copy)/26432.txt" id="26432" sender="phillip.allen@enron.com" subject="Consolidated positions Issues To Do list">1</tf><tf date="2000/09/12 04:23" file="FINDMAIL/HTML_files/1 (5th copy)/1905.txt" id="1905" sender="phillip.allen@enron.com" subject="Contact list for mid market">1</tf><tf date="2000/10/09 07:16" file="FINDMAIL/HTML_files/1 (another copy)/5708.txt" id="5708" sender="phillip.allen@enron.com" subject="Consolidated positions Issues To Do list">1</tf><tf date="2000/10/09 07:00" file="FINDMAIL/HTML_files/1 (4th copy)/6432.txt" id="6432" sender="phillip.allen@enron.com" subject="Consolidated positions Issues To Do list">1</tf><tf date="2001/04/04 07:43" file="FINDMAIL/HTML_files/1 (28th copy)/853.txt" id="853" sender="phillip.allen@enron.com" subject="Re Answers to List">1</tf><tf date="2001/04/18 11:11" file="FINDMAIL/HTML_files/1 (15th copy)/3512.txt" id="3512" sender="phillip.allen@enron.com" subject="approved trader list">1</tf><tf date="2000/09/12 04:23" file="FINDMAIL/HTML_files/1 (10th copy)/8199.txt" id="8199" sender="phillip.allen@enron.com" subject="Contact list for mid market">1</tf><tf date="2001/04/04 07:43" file="FINDMAIL/HTML_files/1 (12th copy)/18853.txt" id="18853" sender="phillip.allen@enron.com" subject="Re Answers to List">1</tf><tf date="2000/03/13 05:31" file="FINDMAIL/HTML_files/1 (12th copy)/18851.txt" id="18851" sender="phillip.allen@enron.com" subject="Priority List">1</tf><tf date="2000/09/12 04:23" file="FINDMAIL/HTML_files/1 (17th copy)/25905.txt" id="25905" sender="phillip.allen@enron.com" subject="Contact list for mid market">1</tf><tf date="2000/03/13 05:31" file="FINDMAIL/HTML_files/1 (7th copy)/21459.txt" id="21459" sender="phillip.allen@enron.com" subject="Priority List">1</tf><tf date="2000/03/13 05:31" file="FINDMAIL/HTML_files/1 (20th copy)/23395.txt" id="23395" sender="phillip.allen@enron.com" subject="Priority List">1</tf><tf date="2000/09/12 04:23" file="FINDMAIL/HTML_files/1 (19th copy)/27988.txt" id="27988" sender="phillip.allen@enron.com" subject="Contact list for mid market">1</tf><tf date="2001/04/18 11:11" file="FINDMAIL/HTML_files/1 (26th copy)/7512.txt" id="7512" sender="phillip.allen@enron.com" subject="approved trader list">1</tf><tf date="2000/10/09 07:00" file="FINDMAIL/HTML_files/1 (16th copy)/22432.txt" id="22432" sender="phillip.allen@enron.com" subject="Consolidated positions Issues To Do list">1</tf><tf date="2000/03/13 05:32" file="FINDMAIL/HTML_files/1 (3rd copy)/19155.txt" id="19155" sender="phillip.allen@enron.com" subject="Priority List">1</tf><tf date="2000/10/09 07:00" file="FINDMAIL/HTML_files/1 (5th copy)/1432.txt" id="1432" sender="phillip.allen@enron.com" subject="Consolidated positions Issues To Do list">1</tf><tf date="2000/10/09 07:00" file="FINDMAIL/HTML_files/1 (another copy)/5182.txt" id="5182" sender="phillip.allen@enron.com" subject="Consolidated positions Issues To Do list">1</tf><tf date="2000/10/09 07:00" file="FINDMAIL/HTML_files/1 (7th copy)/21432.txt" id="21432" sender="phillip.allen@enron.com" subject="Consolidated positions Issues To Do list">1</tf><tf date="2001/03/26 02:03" file="FINDMAIL/HTML_files/1 (14th copy)/13762.txt" id="13762" sender="phillip.allen@enron.com" subject="Current Gas Desk List">1</tf><tf date="1979/12/31 16:00" file="FINDMAIL/HTML_files/1 (10th copy)/8934.txt" id="8934" sender="phillip.allen@enron.com" subject="systems wish list">1</tf><tf date="2000/03/13 05:31" file="FINDMAIL/HTML_files/1 (3rd copy)/19459.txt" id="19459" sender="phillip.allen@enron.com" subject="Priority List">1</tf><tf date="2000/03/13 05:31" file="FINDMAIL/HTML_files/1 (17th copy)/25395.txt" id="25395" sender="phillip.allen@enron.com" subject="Priority List">1</tf><tf date="1979/12/31 16:00" file="FINDMAIL/HTML_files/1 (3rd copy)/19934.txt" id="19934" sender="phillip.allen@enron.com" subject="systems wish list">1</tf><tf date="2000/03/13 05:32" file="FINDMAIL/HTML_files/1 (17th copy)/25155.txt" id="25155" sender="phillip.allen@enron.com" subject="Priority List">1</tf><tf date="2000/10/09 07:16" file="FINDMAIL/HTML_files/1 (3rd copy)/19526.txt" id="19526" sender="phillip.allen@enron.com" subject="Consolidated positions Issues To Do list">1</tf><tf date="2000/10/09 07:16" file="FINDMAIL/HTML_files/1 (12th copy)/18708.txt" id="18708" sender="phillip.allen@enron.com" subject="Consolidated positions Issues To Do list">1</tf><tf date="2000/09/12 04:23" file="FINDMAIL/HTML_files/1/12199.txt" id="12199" sender="phillip.allen@enron.com" subject="Contact list for mid market">1</tf><tf date="2000/10/09 07:00" file="FINDMAIL/HTML_files/1 (6th copy)/16583.txt" id="16583" sender="phillip.allen@enron.com" subject="Consolidated positions Issues To Do list">1</tf><tf date="2000/09/12 04:23" file="FINDMAIL/HTML_files/1 (6th copy)/16199.txt" id="16199" sender="phillip.allen@enron.com" subject="Contact list for mid market">1</tf><tf date="2000/09/12 04:23" file="FINDMAIL/HTML_files/1 (5th copy)/1199.txt" id="1199" sender="phillip.allen@enron.com" subject="Contact list for mid market">1</tf><tf date="2000/03/13 05:31" file="FINDMAIL/HTML_files/1 (another copy)/5459.txt" id="5459" sender="phillip.allen@enron.com" subject="Priority List">1</tf><tf date="1979/12/31 16:00" file="FINDMAIL/HTML_files/1 (20th copy)/23934.txt" id="23934" sender="phillip.allen@enron.com" subject="systems wish list">1</tf><tf date="2001/04/04 07:43" file="FINDMAIL/HTML_files/1 (17th copy)/25853.txt" id="25853" sender="phillip.allen@enron.com" subject="Re Answers to List">1</tf><tf date="2000/10/09 07:00" file="FINDMAIL/HTML_files/1 (19th copy)/27182.txt" id="27182" sender="phillip.allen@enron.com" subject="Consolidated positions Issues To Do list">1</tf><tf date="2000/03/13 05:31" file="FINDMAIL/HTML_files/1 (24th copy)/14395.txt" id="14395" sender="phillip.allen@enron.com" subject="Priority List">1</tf><tf date="1979/12/31 16:00" file="FINDMAIL/HTML_files/1 (copy)/10934.txt" id="10934" sender="phillip.allen@enron.com" subject="systems wish list">1</tf><tf date="2000/09/12 04:23" file="FINDMAIL/HTML_files/1 (3rd copy)/19988.txt" id="19988" sender="phillip.allen@enron.com" subject="Contact list for mid market">1</tf><tf date="2000/03/13 05:31" file="FINDMAIL/HTML_files/1 (29th copy)/29851.txt" id="29851" sender="phillip.allen@enron.com" subject="Priority List">1</tf><tf date="2001/03/26 02:03" file="FINDMAIL/HTML_files/1 (29th copy)/29762.txt" id="29762" sender="phillip.allen@enron.com" subject="Current Gas Desk List">1</tf><tf date="2000/10/09 07:16" file="FINDMAIL/HTML_files/1 (21st copy)/20708.txt" id="20708" sender="phillip.allen@enron.com" subject="Consolidated positions Issues To Do list">1</tf><tf date="1979/12/31 16:00" file="FINDMAIL/HTML_files/1 (17th copy)/25271.txt" id="25271" sender="phillip.allen@enron.com" subject="systems wish list">1</tf><tf date="1979/12/31 16:00" file="FINDMAIL/HTML_files/1 (5th copy)/1271.txt" id="1271" sender="phillip.allen@enron.com" subject="systems wish list">1</tf><tf date="2000/09/12 04:23" file="FINDMAIL/HTML_files/1 (18th copy)/26199.txt" id="26199" sender="phillip.allen@enron.com" subject="Contact list for mid market">1</tf><tf date="2001/03/26 02:03" file="FINDMAIL/HTML_files/1 (20th copy)/23762.txt" id="23762" sender="phillip.allen@enron.com" subject="Current Gas Desk List">1</tf><tf date="2000/10/09 07:16" file="FINDMAIL/HTML_files/1 (15th copy)/3708.txt" id="3708" sender="phillip.allen@enron.com" subject="Consolidated positions Issues To Do list">1</tf><tf date="2000/03/13 05:32" file="FINDMAIL/HTML_files/1 (7th copy)/21155.txt" id="21155" sender="phillip.allen@enron.com" subject="Priority List">1</tf><tf date="1979/12/31 16:00" file="FINDMAIL/HTML_files/1 (13th copy)/24934.txt" id="24934" sender="phillip.allen@enron.com" subject="systems wish list">1</tf><tf date="2001/03/26 02:03" file="FINDMAIL/HTML_files/1 (24th copy)/14762.txt" id="14762" sender="phillip.allen@enron.com" subject="Current Gas Desk List">1</tf><tf date="2001/03/26 02:03" file="FINDMAIL/HTML_files/1 (10th copy)/8762.txt" id="8762" sender="phillip.allen@enron.com" subject="Current Gas Desk List">1</tf><tf date="2000/10/09 07:00" file="FINDMAIL/HTML_files/1 (25th copy)/17182.txt" id="17182" sender="phillip.allen@enron.com" subject="Consolidated positions Issues To Do list">1</tf><tf date="2000/10/09 07:16" file="FINDMAIL/HTML_files/1 (7th copy)/21484.txt" id="21484" sender="phillip.allen@enron.com" subject="Consolidated positions Issues To Do list">1</tf><tf date="2001/03/26 02:03" file="FINDMAIL/HTML_files/1 (25th copy)/17762.txt" id="17762" sender="phillip.allen@enron.com" subject="Current Gas Desk List">1</tf><tf date="2000/09/12 04:23" file="FINDMAIL/HTML_files/1 (23rd copy)/9988.txt" id="9988" sender="phillip.allen@enron.com" subject="Contact list for mid market">1</tf><tf date="1979/12/31 16:00" file="FINDMAIL/HTML_files/1 (7th copy)/21271.txt" id="21271" sender="phillip.allen@enron.com" subject="systems wish list">1</tf><tf date="2000/10/09 07:16" file="FINDMAIL/HTML_files/1 (17th copy)/25708.txt" id="25708" sender="phillip.allen@enron.com" subject="Consolidated positions Issues To Do list">1</tf><tf date="1979/12/31 16:00" file="FINDMAIL/HTML_files/1 (16th copy)/22934.txt" id="22934" sender="phillip.allen@enron.com" subject="systems wish list">1</tf><tf date="1979/12/31 16:00" file="FINDMAIL/HTML_files/1 (18th copy)/26934.txt" id="26934" sender="phillip.allen@enron.com" subject="systems wish list">1</tf><tf date="1979/12/31 16:00" file="FINDMAIL/HTML_files/1 (14th copy)/13934.txt" id="13934" sender="phillip.allen@enron.com" subject="systems wish list">1</tf><tf date="2000/09/12 04:23" file="FINDMAIL/HTML_files/1 (10th copy)/8988.txt" id="8988" sender="phillip.allen@enron.com" subject="Contact list for mid market">1</tf><tf date="2000/10/09 07:00" file="FINDMAIL/HTML_files/1 (another copy)/5583.txt" id="5583" sender="phillip.allen@enron.com" subject="Consolidated positions Issues To Do list">1</tf><tf date="2001/03/26 02:03" file="FINDMAIL/HTML_files/1 (19th copy)/27762.txt" id="27762" sender="phillip.allen@enron.com" subject="Current Gas Desk List">1</tf><tf date="2000/10/09 07:00" file="FINDMAIL/HTML_files/1 (9th copy)/28182.txt" id="28182" sender="phillip.allen@enron.com" subject="Consolidated positions Issues To Do list">1</tf><tf date="2000/03/13 05:32" file="FINDMAIL/HTML_files/1 (16th copy)/22155.txt" id="22155" sender="phillip.allen@enron.com" subject="Priority List">1</tf><tf date="2000/03/13 05:31" file="FINDMAIL/HTML_files/1 (26th copy)/7459.txt" id="7459" sender="phillip.allen@enron.com" subject="Priority List">1</tf><tf date="2000/03/13 05:32" file="FINDMAIL/HTML_files/1 (11th copy)/2155.txt" id="2155" sender="phillip.allen@enron.com" subject="Priority List">1</tf><tf date="2001/04/18 01:11" file="FINDMAIL/HTML_files/1 (20th copy)/23298.txt" id="23298" sender="phillip.allen@enron.com" subject="approved trader list">1</tf><tf date="1979/12/31 16:00" file="FINDMAIL/HTML_files/1/12271.txt" id="12271" sender="phillip.allen@enron.com" subject="systems wish list">1</tf><tf date="2000/09/12 04:23" file="FINDMAIL/HTML_files/1 (22nd copy)/4988.txt" id="4988" sender="phillip.allen@enron.com" subject="Contact list for mid market">1</tf><tf date="2000/10/09 07:16" file="FINDMAIL/HTML_files/1 (14th copy)/13484.txt" id="13484" sender="phillip.allen@enron.com" subject="Consolidated positions Issues To Do list">1</tf><tf date="1979/12/31 16:00" file="FINDMAIL/HTML_files/1 (28th copy)/934.txt" id="934" sender="phillip.allen@enron.com" subject="systems wish list">1</tf><tf date="2000/10/09 07:16" file="FINDMAIL/HTML_files/1 (copy)/10526.txt" id="10526" sender="phillip.allen@enron.com" subject="Consolidated positions Issues To Do list">1</tf><tf date="2000/09/12 04:23" file="FINDMAIL/HTML_files/1 (21st copy)/20905.txt" id="20905" sender="phillip.allen@enron.com" subject="Contact list for mid market">1</tf><tf date="2000/10/09 07:16" file="FINDMAIL/HTML_files/1 (12th copy)/18484.txt" id="18484" sender="phillip.allen@enron.com" subject="Consolidated positions Issues To Do list">1</tf><tf date="2000/10/09 07:16" file="FINDMAIL/HTML_files/1 (19th copy)/27484.txt" id="27484" sender="phillip.allen@enron.com" subject="Consolidated positions Issues To Do list">1</tf><tf date="1979/12/31 16:00" file="FINDMAIL/HTML_files/1 (15th copy)/3934.txt" id="3934" sender="phillip.allen@enron.com" subject="systems wish list">1</tf><tf date="2000/10/09 07:16" file="FINDMAIL/HTML_files/1 (23rd copy)/9708.txt" id="9708" sender="phillip.allen@enron.com" subject="Consolidated positions Issues To Do list">1</tf><tf date="1979/12/31 16:00" file="FINDMAIL/HTML_files/1 (20th copy)/23271.txt" id="23271" sender="phillip.allen@enron.com" subject="systems wish list">1</tf><tf date="1979/12/31 16:00" file="FINDMAIL/HTML_files/1 (8th copy)/11271.txt" id="11271" sender="phillip.allen@enron.com" subject="systems wish list">1</tf><tf date="2001/04/18 11:11" file="FINDMAIL/HTML_files/1 (21st copy)/20512.txt" id="20512" sender="phillip.allen@enron.com" subject="approved trader list">1</tf><tf date="2000/09/12 04:23" file="FINDMAIL/HTML_files/1 (9th copy)/28988.txt" id="28988" sender="phillip.allen@enron.com" subject="Contact list for mid market">1</tf><tf date="2000/10/09 07:16" file="FINDMAIL/HTML_files/1 (25th copy)/17484.txt" id="17484" sender="phillip.allen@enron.com" subject="Consolidated positions Issues To Do list">1</tf><tf date="2000/03/13 05:32" file="FINDMAIL/HTML_files/1 (14th copy)/13155.txt" id="13155" sender="phillip.allen@enron.com" subject="Priority List">1</tf><tf date="2000/09/12 04:23" file="FINDMAIL/HTML_files/1 (23rd copy)/9905.txt" id="9905" sender="phillip.allen@enron.com" subject="Contact list for mid market">1</tf><tf date="2001/04/04 07:43" file="FINDMAIL/HTML_files/1 (26th copy)/7853.txt" id="7853" sender="phillip.allen@enron.com" subject="Re Answers to List">1</tf><tf date="2000/10/09 07:16" file="FINDMAIL/HTML_files/1 (22nd copy)/4484.txt" id="4484" sender="phillip.allen@enron.com" subject="Consolidated positions Issues To Do list">1</tf><tf date="1979/12/31 16:00" file="FINDMAIL/HTML_files/1 (16th copy)/22271.txt" id="22271" sender="phillip.allen@enron.com" subject="systems wish list">1</tf><tf date="2000/10/09 07:16" file="FINDMAIL/HTML_files/1 (26th copy)/7526.txt" id="7526" sender="phillip.allen@enron.com" subject="Consolidated positions Issues To Do list">1</tf><tf date="2000/09/12 04:23" file="FINDMAIL/HTML_files/1 (8th copy)/11905.txt" id="11905" sender="phillip.allen@enron.com" subject="Contact list for mid market">1</tf><tf date="2000/10/09 07:16" file="FINDMAIL/HTML_files/1 (28th copy)/708.txt" id="708" sender="phillip.allen@enron.com" subject="Consolidated positions Issues To Do list">1</tf><tf date="2000/09/12 04:23" file="FINDMAIL/HTML_files/1 (11th copy)/2905.txt" id="2905" sender="phillip.allen@enron.com" subject="Contact list for mid market">1</tf><tf date="2000/09/12 04:23" file="FINDMAIL/HTML_files/1/12905.txt" id="12905" sender="phillip.allen@enron.com" subject="Contact list for mid market">1</tf><tf date="2000/09/12 04:23" file="FINDMAIL/HTML_files/1 (12th copy)/18988.txt" id="18988" sender="phillip.allen@enron.com" subject="Contact list for mid market">1</tf><tf date="2000/10/09 07:00" file="FINDMAIL/HTML_files/1 (19th copy)/27432.txt" id="27432" sender="phillip.allen@enron.com" subject="Consolidated positions Issues To Do list">1</tf><tf date="2000/03/13 05:31" file="FINDMAIL/HTML_files/1 (28th copy)/395.txt" id="395" sender="phillip.allen@enron.com" subject="Priority List">1</tf><tf date="2000/10/09 07:16" file="FINDMAIL/HTML_files/1 (5th copy)/1484.txt" id="1484" sender="phillip.allen@enron.com" subject="Consolidated positions Issues To Do list">1</tf><tf date="2000/09/12 04:23" file="FINDMAIL/HTML_files/1 (25th copy)/17905.txt" id="17905" sender="phillip.allen@enron.com" subject="Contact list for mid market">1</tf><tf date="2000/10/09 07:16" file="FINDMAIL/HTML_files/1 (9th copy)/28526.txt" id="28526" sender="phillip.allen@enron.com" subject="Consolidated positions Issues To Do list">1</tf><tf date="2000/09/12 04:23" file="FINDMAIL/HTML_files/1 (24th copy)/14199.txt" id="14199" sender="phillip.allen@enron.com" subject="Contact list for mid market">1</tf><tf date="2000/10/09 07:00" file="FINDMAIL/HTML_files/1 (29th copy)/29583.txt" id="29583" sender="phillip.allen@enron.com" subject="Consolidated positions Issues To Do list">1</tf><tf date="2000/09/12 04:23" file="FINDMAIL/HTML_files/1 (21st copy)/20199.txt" id="20199" sender="phillip.allen@enron.com" subject="Contact list for mid market">1</tf><tf date="2001/04/18 01:11" file="FINDMAIL/HTML_files/1 (24th copy)/14298.txt" id="14298" sender="phillip.allen@enron.com" subject="approved trader list">1</tf><tf date="2000/10/09 07:16" file="FINDMAIL/HTML_files/1 (3rd copy)/19708.txt" id="19708" sender="phillip.allen@enron.com" subject="Consolidated positions Issues To Do list">1</tf><tf date="2000/03/13 05:31" file="FINDMAIL/HTML_files/1 (27th copy)/15851.txt" id="15851" sender="phillip.allen@enron.com" subject="Priority List">1</tf><tf date="2000/10/09 07:00" file="FINDMAIL/HTML_files/1 (4th copy)/6583.txt" id="6583" sender="phillip.allen@enron.com" subject="Consolidated positions Issues To Do list">1</tf><tf date="2000/10/09 07:00" file="FINDMAIL/HTML_files/1 (28th copy)/583.txt" id="583" sender="phillip.allen@enron.com" subject="Consolidated positions Issues To Do list">1</tf><tf date="2000/10/09 07:16" file="FINDMAIL/HTML_files/1 (27th copy)/15526.txt" id="15526" sender="phillip.allen@enron.com" subject="Consolidated positions Issues To Do list">1</tf><tf date="2001/04/18 11:11" file="FINDMAIL/HTML_files/1 (3rd copy)/19512.txt" id="19512" sender="phillip.allen@enron.com" subject="approved trader list">1</tf><tf date="2000/10/09 07:16" file="FINDMAIL/HTML_files/1 (6th copy)/16484.txt" id="16484" sender="phillip.allen@enron.com" subject="Consolidated positions Issues To Do list">1</tf><tf date="2001/04/04 07:43" file="FINDMAIL/HTML_files/1 (another copy)/5853.txt" id="5853" sender="phillip.allen@enron.com" subject="Re Answers to List">1</tf><tf date="2000/10/09 07:16" file="FINDMAIL/HTML_files/1 (27th copy)/15484.txt" id="15484" sender="phillip.allen@enron.com" subject="Consolidated positions Issues To Do list">1</tf><tf date="2000/03/13 05:32" file="FINDMAIL/HTML_files/1 (15th copy)/3155.txt" id="3155" sender="phillip.allen@enron.com" subject="Priority List">1</tf><tf date="2000/10/09 07:00" file="FINDMAIL/HTML_files/1 (14th copy)/13432.txt" id="13432" sender="phillip.allen@enron.com" subject="Consolidated positions Issues To Do list">1</tf><tf date="2000/10/09 07:00" file="FINDMAIL/HTML_files/1 (17th copy)/25432.txt" id="25432" sender="phillip.allen@enron.com" subject="Consolidated positions Issues To Do list">1</tf><tf date="2000/10/09 07:16" file="FINDMAIL/HTML_files/1 (16th copy)/22708.txt" id="22708" sender="phillip.allen@enron.com" subject="Consolidated positions Issues To Do list">1</tf><tf date="2000/10/09 07:16" file="FINDMAIL/HTML_files/1 (7th copy)/21526.txt" id="21526" sender="phillip.allen@enron.com" subject="Consolidated positions Issues To Do list">1</tf><tf date="2000/03/13 05:31" file="FINDMAIL/HTML_files/1 (20th copy)/23459.txt" id="23459" sender="phillip.allen@enron.com" subject="Priority List">1</tf><tf date="1979/12/31 16:00" file="FINDMAIL/HTML_files/1 (11th copy)/2271.txt" id="2271" sender="phillip.allen@enron.com" subject="systems wish list">1</tf><tf date="2000/10/09 07:16" file="FINDMAIL/HTML_files/1 (13th copy)/24526.txt" id="24526" sender="phillip.allen@enron.com" subject="Consolidated positions Issues To Do list">1</tf><tf date="2000/10/09 07:16" file="FINDMAIL/HTML_files/1 (18th copy)/26484.txt" id="26484" sender="phillip.allen@enron.com" subject="Consolidated positions Issues To Do list">1</tf><tf date="2000/09/12 04:23" file="FINDMAIL/HTML_files/1 (copy)/10905.txt" id="10905" sender="phillip.allen@enron.com" subject="Contact list for mid market">1</tf><tf date="2000/09/12 04:23" file="FINDMAIL/HTML_files/1 (20th copy)/23988.txt" id="23988" sender="phillip.allen@enron.com" subject="Contact list for mid market">1</tf><tf date="2000/03/13 05:31" file="FINDMAIL/HTML_files/1 (8th copy)/11459.txt" id="11459" sender="phillip.allen@enron.com" subject="Priority List">1</tf><tf date="2000/03/13 05:31" file="FINDMAIL/HTML_files/1 (6th copy)/16395.txt" id="16395" sender="phillip.allen@enron.com" subject="Priority List">1</tf><tf date="2001/04/18 11:11" file="FINDMAIL/HTML_files/1 (28th copy)/512.txt" id="512" sender="phillip.allen@enron.com" subject="approved trader list">1</tf><tf date="2000/10/09 07:00" file="FINDMAIL/HTML_files/1 (29th copy)/29432.txt" id="29432" sender="phillip.allen@enron.com" subject="Consolidated positions Issues To Do list">1</tf><tf date="2000/03/13 05:31" file="FINDMAIL/HTML_files/1 (28th copy)/459.txt" id="459" sender="phillip.allen@enron.com" subject="Priority List">1</tf><tf date="2000/03/13 05:31" file="FINDMAIL/HTML_files/1 (11th copy)/2459.txt" id="2459" sender="phillip.allen@enron.com" subject="Priority List">1</tf><tf date="2000/10/09 07:00" file="FINDMAIL/HTML_files/1 (25th copy)/17432.txt" id="17432" sender="phillip.allen@enron.com" subject="Consolidated positions Issues To Do list">1</tf><tf date="2000/10/09 07:00" file="FINDMAIL/HTML_files/1 (22nd copy)/4182.txt" id="4182" sender="phillip.allen@enron.com" subject="Consolidated positions Issues To Do list">1</tf><tf date="2000/10/09 07:00" file="FINDMAIL/HTML_files/1 (6th copy)/16432.txt" id="16432" sender="phillip.allen@enron.com" subject="Consolidated positions Issues To Do list">1</tf><tf date="2000/03/13 05:31" file="FINDMAIL/HTML_files/1 (26th copy)/7851.txt" id="7851" sender="phillip.allen@enron.com" subject="Priority List">1</tf><tf date="2000/10/09 07:00" file="FINDMAIL/HTML_files/1 (22nd copy)/4432.txt" id="4432" sender="phillip.allen@enron.com" subject="Consolidated positions Issues To Do list">1</tf><tf date="2001/04/18 01:11" file="FINDMAIL/HTML_files/1 (10th copy)/8298.txt" id="8298" sender="phillip.allen@enron.com" subject="approved trader list">1</tf><tf date="2000/03/13 05:32" file="FINDMAIL/HTML_files/1 (8th copy)/11155.txt" id="11155" sender="phillip.allen@enron.com" subject="Priority List">1</tf><tf date="2000/10/09 07:16" file="FINDMAIL/HTML_files/1 (13th copy)/24484.txt" id="24484" sender="phillip.allen@enron.com" subject="Consolidated positions Issues To Do list">1</tf><tf date="2000/09/12 04:23" file="FINDMAIL/HTML_files/1 (17th copy)/25988.txt" id="25988" sender="phillip.allen@enron.com" subject="Contact list for mid market">1</tf><tf date="2000/10/09 07:00" file="FINDMAIL/HTML_files/1 (24th copy)/14432.txt" id="14432" sender="phillip.allen@enron.com" subject="Consolidated positions Issues To Do list">1</tf><tf date="2000/10/09 07:16" file="FINDMAIL/HTML_files/1 (9th copy)/28708.txt" id="28708" sender="phillip.allen@enron.com" subject="Consolidated positions Issues To Do list">1</tf><tf date="2001/04/18 11:11" file="FINDMAIL/HTML_files/1 (13th copy)/24512.txt" id="24512" sender="phillip.allen@enron.com" subject="approved trader list">1</tf><tf date="2000/10/09 07:00" file="FINDMAIL/HTML_files/1 (28th copy)/182.txt" id="182" sender="phillip.allen@enron.com" subject="Consolidated positions Issues To Do list">1</tf><tf date="2001/04/18 01:11" file="FINDMAIL/HTML_files/1 (13th copy)/24298.txt" id="24298" sender="phillip.allen@enron.com" subject="approved trader list">1</tf><tf date="2000/03/13 05:32" file="FINDMAIL/HTML_files/1 (29th copy)/29155.txt" id="29155" sender="phillip.allen@enron.com" subject="Priority List">1</tf><tf date="1979/12/31 16:00" file="FINDMAIL/HTML_files/1 (7th copy)/21934.txt" id="21934" sender="phillip.allen@enron.com" subject="systems wish list">1</tf><tf date="2000/09/12 04:23" file="FINDMAIL/HTML_files/1 (26th copy)/7988.txt" id="7988" sender="phillip.allen@enron.com" subject="Contact list for mid market">1</tf><tf date="2000/03/13 05:32" file="FINDMAIL/HTML_files/1 (20th copy)/23155.txt" id="23155" sender="phillip.allen@enron.com" subject="Priority List">1</tf><tf date="2000/03/13 05:32" file="FINDMAIL/HTML_files/1 (copy)/10155.txt" id="10155" sender="phillip.allen@enron.com" subject="Priority List">1</tf><tf date="2000/03/13 05:31" file="FINDMAIL/HTML_files/1 (8th copy)/11395.txt" id="11395" sender="phillip.allen@enron.com" subject="Priority List">1</tf><tf date="2000/10/09 07:16" file="FINDMAIL/HTML_files/1 (15th copy)/3526.txt" id="3526" sender="phillip.allen@enron.com" subject="Consolidated positions Issues To Do list">1</tf><tf date="2000/10/09 07:00" file="FINDMAIL/HTML_files/1 (23rd copy)/9583.txt" id="9583" sender="phillip.allen@enron.com" subject="Consolidated positions Issues To Do list">1</tf><tf date="2001/04/18 01:11" file="FINDMAIL/HTML_files/1 (19th copy)/27298.txt" id="27298" sender="phillip.allen@enron.com" subject="approved trader list">1</tf><tf date="2000/10/09 07:16" file="FINDMAIL/HTML_files/1 (18th copy)/26526.txt" id="26526" sender="phillip.allen@enron.com" subject="Consolidated positions Issues To Do list">1</tf><tf date="2000/03/13 05:31" file="FINDMAIL/HTML_files/1 (copy)/10395.txt" id="10395" sender="phillip.allen@enron.com" subject="Priority List">1</tf><tf date="2000/09/12 04:23" file="FINDMAIL/HTML_files/1 (14th copy)/13199.txt" id="13199" sender="phillip.allen@enron.com" subject="Contact list for mid market">1</tf><tf date="2000/10/09 07:00" file="FINDMAIL/HTML_files/1 (10th copy)/8182.txt" id="8182" sender="phillip.allen@enron.com" subject="Consolidated positions Issues To Do list">1</tf><tf date="2000/10/09 07:00" file="FINDMAIL/HTML_files/1 (13th copy)/24583.txt" id="24583" sender="phillip.allen@enron.com" subject="Consolidated positions Issues To Do list">1</tf><tf date="2001/03/26 02:03" file="FINDMAIL/HTML_files/1 (26th copy)/7762.txt" id="7762" sender="phillip.allen@enron.com" subject="Current Gas Desk List">1</tf><tf date="1979/12/31 16:00" file="FINDMAIL/HTML_files/1 (13th copy)/24271.txt" id="24271" sender="phillip.allen@enron.com" subject="systems wish list">1</tf><tf date="2000/10/09 07:16" file="FINDMAIL/HTML_files/1 (27th copy)/15708.txt" id="15708" sender="phillip.allen@enron.com" subject="Consolidated positions Issues To Do list">1</tf><tf date="2000/09/12 04:23" file="FINDMAIL/HTML_files/1 (15th copy)/3905.txt" id="3905" sender="phillip.allen@enron.com" subject="Contact list for mid market">1</tf><tf date="1979/12/31 16:00" file="FINDMAIL/HTML_files/1 (copy)/10271.txt" id="10271" sender="phillip.allen@enron.com" subject="systems wish list">1</tf><tf date="2001/04/18 01:11" file="FINDMAIL/HTML_files/1 (18th copy)/26298.txt" id="26298" sender="phillip.allen@enron.com" subject="approved trader list">1</tf><tf date="2000/10/09 07:16" file="FINDMAIL/HTML_files/1 (8th copy)/11526.txt" id="11526" sender="phillip.allen@enron.com" subject="Consolidated positions Issues To Do list">1</tf><tf date="2001/03/26 02:03" file="FINDMAIL/HTML_files/1 (22nd copy)/4762.txt" id="4762" sender="phillip.allen@enron.com" subject="Current Gas Desk List">1</tf><tf date="2001/04/18 01:11" file="FINDMAIL/HTML_files/1 (16th copy)/22298.txt" id="22298" sender="phillip.allen@enron.com" subject="approved trader list">1</tf><tf date="2000/10/09 07:16" file="FINDMAIL/HTML_files/1 (16th copy)/22526.txt" id="22526" sender="phillip.allen@enron.com" subject="Consolidated positions Issues To Do list">1</tf><tf date="2000/03/13 05:32" file="FINDMAIL/HTML_files/1 (24th copy)/14155.txt" id="14155" sender="phillip.allen@enron.com" subject="Priority List">1</tf><tf date="2000/03/13 05:31" file="FINDMAIL/HTML_files/1 (21st copy)/20395.txt" id="20395" sender="phillip.allen@enron.com" subject="Priority List">1</tf><tf date="1979/12/31 16:00" file="FINDMAIL/HTML_files/1 (12th copy)/18934.txt" id="18934" sender="phillip.allen@enron.com" subject="systems wish list">1</tf><tf date="2000/09/12 04:23" file="FINDMAIL/HTML_files/1 (another copy)/5199.txt" id="5199" sender="phillip.allen@enron.com" subject="Contact list for mid market">1</tf><tf date="2000/03/13 05:31" file="FINDMAIL/HTML_files/1 (18th copy)/26459.txt" id="26459" sender="phillip.allen@enron.com" subject="Priority List">1</tf><tf date="1979/12/31 16:00" file="FINDMAIL/HTML_files/1 (29th copy)/29271.txt" id="29271" sender="phillip.allen@enron.com" subject="systems wish list">1</tf><tf date="2000/10/09 07:00" file="FINDMAIL/HTML_files/1 (7th copy)/21583.txt" id="21583" sender="phillip.allen@enron.com" subject="Consolidated positions Issues To Do list">1</tf><tf date="2000/10/09 07:16" file="FINDMAIL/HTML_files/1 (12th copy)/18526.txt" id="18526" sender="phillip.allen@enron.com" subject="Consolidated positions Issues To Do list">1</tf><tf date="2000/10/09 07:16" file="FINDMAIL/HTML_files/1 (24th copy)/14484.txt" id="14484" sender="phillip.allen@enron.com" subject="Consolidated positions Issues To Do list">1</tf><tf date="2000/10/09 07:16" file="FINDMAIL/HTML_files/1 (16th copy)/22484.txt" id="22484" sender="phillip.allen@enron.com" subject="Consolidated positions Issues To Do list">1</tf><tf date="2000/03/13 05:31" file="FINDMAIL/HTML_files/1 (9th copy)/28459.txt" id="28459" sender="phillip.allen@enron.com" subject="Priority List">1</tf><tf date="1979/12/31 16:00" file="FINDMAIL/HTML_files/1 (24th copy)/14271.txt" id="14271" sender="phillip.allen@enron.com" subject="systems wish list">1</tf><tf date="2001/04/18 11:11" file="FINDMAIL/HTML_files/1 (9th copy)/28512.txt" id="28512" sender="phillip.allen@enron.com" subject="approved trader list">1</tf><tf date="1979/12/31 16:00" file="FINDMAIL/HTML_files/1 (25th copy)/17934.txt" id="17934" sender="phillip.allen@enron.com" subject="systems wish list">1</tf><tf date="2000/10/09 07:00" file="FINDMAIL/HTML_files/1 (18th copy)/26182.txt" id="26182" sender="phillip.allen@enron.com" subject="Consolidated positions Issues To Do list">1</tf><tf date="2000/10/09 07:00" file="FINDMAIL/HTML_files/1 (26th copy)/7182.txt" id="7182" sender="phillip.allen@enron.com" subject="Consolidated positions Issues To Do list">1</tf><tf date="2000/09/12 04:23" file="FINDMAIL/HTML_files/1 (20th copy)/23905.txt" id="23905" sender="phillip.allen@enron.com" subject="Contact list for mid market">1</tf><tf date="2000/10/09 07:00" file="FINDMAIL/HTML_files/1 (11th copy)/2182.txt" id="2182" sender="phillip.allen@enron.com" subject="Consolidated positions Issues To Do list">1</tf><tf date="2001/03/26 02:03" file="FINDMAIL/HTML_files/1/12762.txt" id="12762" sender="phillip.allen@enron.com" subject="Current Gas Desk List">1</tf><tf date="1979/12/31 16:00" file="FINDMAIL/HTML_files/1 (another copy)/5934.txt" id="5934" sender="phillip.allen@enron.com" subject="systems wish list">1</tf><tf date="2000/03/13 05:31" file="FINDMAIL/HTML_files/1 (27th copy)/15395.txt" id="15395" sender="phillip.allen@enron.com" subject="Priority List">1</tf><tf date="2001/04/18 01:11" file="FINDMAIL/HTML_files/1 (6th copy)/16298.txt" id="16298" sender="phillip.allen@enron.com" subject="approved trader list">1</tf><tf date="2001/03/26 02:03" file="FINDMAIL/HTML_files/1 (5th copy)/1762.txt" id="1762" sender="phillip.allen@enron.com" subject="Current Gas Desk List">1</tf><tf date="2000/10/09 07:16" file="FINDMAIL/HTML_files/1 (17th copy)/25484.txt" id="25484" sender="phillip.allen@enron.com" subject="Consolidated positions Issues To Do list">1</tf><tf date="2000/09/12 04:23" file="FINDMAIL/HTML_files/1 (27th copy)/15905.txt" id="15905" sender="phillip.allen@enron.com" subject="Contact list for mid market">1</tf><tf date="2000/10/09 07:16" file="FINDMAIL/HTML_files/1/12484.txt" id="12484" sender="phillip.allen@enron.com" subject="Consolidated positions Issues To Do list">1</tf><tf date="2000/03/13 05:31" file="FINDMAIL/HTML_files/1 (27th copy)/15459.txt" id="15459" sender="phillip.allen@enron.com" subject="Priority List">1</tf><tf date="2001/04/18 11:11" file="FINDMAIL/HTML_files/1 (20th copy)/23512.txt" id="23512" sender="phillip.allen@enron.com" subject="approved trader list">1</tf><tf date="2000/03/13 05:32" file="FINDMAIL/HTML_files/1 (10th copy)/8155.txt" id="8155" sender="phillip.allen@enron.com" subject="Priority List">1</tf><tf date="2000/09/12 04:23" file="FINDMAIL/HTML_files/1 (7th copy)/21905.txt" id="21905" sender="phillip.allen@enron.com" subject="Contact list for mid market">1</tf><tf date="2000/09/12 04:23" file="FINDMAIL/HTML_files/1 (29th copy)/29988.txt" id="29988" sender="phillip.allen@enron.com" subject="Contact list for mid market">1</tf><tf date="1979/12/31 16:00" file="FINDMAIL/HTML_files/1 (6th copy)/16271.txt" id="16271" sender="phillip.allen@enron.com" subject="systems wish list">1</tf><tf date="2001/04/18 11:11" file="FINDMAIL/HTML_files/1 (27th copy)/15512.txt" id="15512" sender="phillip.allen@enron.com" subject="approved trader list">1</tf><tf date="2000/03/13 05:32" file="FINDMAIL/HTML_files/1 (12th copy)/18155.txt" id="18155" sender="phillip.allen@enron.com" subject="Priority List">1</tf><tf date="2000/03/13 05:31" file="FINDMAIL/HTML_files/1 (13th copy)/24395.txt" id="24395" sender="phillip.allen@enron.com" subject="Priority List">1</tf><tf date="2000/10/09 07:16" file="FINDMAIL/HTML_files/1 (11th copy)/2526.txt" id="2526" sender="phillip.allen@enron.com" subject="Consolidated positions Issues To Do list">1</tf><tf date="2000/10/09 07:16" file="FINDMAIL/HTML_files/1 (11th copy)/2484.txt" id="2484" sender="phillip.allen@enron.com" subject="Consolidated positions Issues To Do list">1</tf><tf date="2000/09/12 04:23" file="FINDMAIL/HTML_files/1 (22nd copy)/4905.txt" id="4905" sender="phillip.allen@enron.com" subject="Contact list for mid market">1</tf><tf date="2000/10/09 07:00" file="FINDMAIL/HTML_files/1/12182.txt" id="12182" sender="phillip.allen@enron.com" subject="Consolidated positions Issues To Do list">1</tf><tf date="2000/09/12 04:23" file="FINDMAIL/HTML_files/1 (8th copy)/11199.txt" id="11199" sender="phillip.allen@enron.com" subject="Contact list for mid market">1</tf><tf date="2000/09/12 04:23" file="FINDMAIL/HTML_files/1 (26th copy)/7199.txt" id="7199" sender="phillip.allen@enron.com" subject="Contact list for mid market">1</tf><tf date="1979/12/31 16:00" file="FINDMAIL/HTML_files/1 (25th copy)/17271.txt" id="17271" sender="phillip.allen@enron.com" subject="systems wish list">1</tf><tf date="2000/10/09 07:16" file="FINDMAIL/HTML_files/1 (8th copy)/11708.txt" id="11708" sender="phillip.allen@enron.com" subject="Consolidated positions Issues To Do list">1</tf><tf date="1979/12/31 16:00" file="FINDMAIL/HTML_files/1 (18th copy)/26271.txt" id="26271" sender="phillip.allen@enron.com" subject="systems wish list">1</tf><tf date="2001/04/04 07:43" file="FINDMAIL/HTML_files/1 (29th copy)/29853.txt" id="29853" sender="phillip.allen@enron.com" subject="Re Answers to List">1</tf><tf date="2000/10/09 07:00" file="FINDMAIL/HTML_files/1 (9th copy)/28583.txt" id="28583" sender="phillip.allen@enron.com" subject="Consolidated positions Issues To Do list">1</tf><tf date="2000/09/12 04:23" file="FINDMAIL/HTML_files/1 (3rd copy)/19905.txt" id="19905" sender="phillip.allen@enron.com" subject="Contact list for mid market">1</tf><tf date="2000/03/13 05:31" file="FINDMAIL/HTML_files/1 (26th copy)/7395.txt" id="7395" sender="phillip.allen@enron.com" subject="Priority List">1</tf><tf date="1979/12/31 16:00" file="FINDMAIL/HTML_files/1 (23rd copy)/9271.txt" id="9271" sender="phillip.allen@enron.com" subject="systems wish list">1</tf><tf date="2000/10/09 07:00" file="FINDMAIL/HTML_files/1 (10th copy)/8432.txt" id="8432" sender="phillip.allen@enron.com" subject="Consolidated positions Issues To Do list">1</tf><tf date="2000/10/09 07:16" file="FINDMAIL/HTML_files/1 (11th copy)/2708.txt" id="2708" sender="phillip.allen@enron.com" subject="Consolidated positions Issues To Do list">1</tf><tf date="2000/09/12 04:23" file="FINDMAIL/HTML_files/1 (13th copy)/24199.txt" id="24199" sender="phillip.allen@enron.com" subject="Contact list for mid market">1</tf><tf date="2000/09/12 04:23" file="FINDMAIL/HTML_files/1 (9th copy)/28905.txt" id="28905" sender="phillip.allen@enron.com" subject="Contact list for mid market">1</tf><tf date="1979/12/31 16:00" file="FINDMAIL/HTML_files/1 (6th copy)/16934.txt" id="16934" sender="phillip.allen@enron.com" subject="systems wish list">1</tf><tf date="2000/10/09 07:00" file="FINDMAIL/HTML_files/1/12432.txt" id="12432" sender="phillip.allen@enron.com" subject="Consolidated positions Issues To Do list">1</tf><tf date="2001/04/18 01:11" file="FINDMAIL/HTML_files/1 (27th copy)/15298.txt" id="15298" sender="phillip.allen@enron.com" subject="approved trader list">1</tf><tf date="2001/03/26 02:03" file="FINDMAIL/HTML_files/1 (21st copy)/20762.txt" id="20762" sender="phillip.allen@enron.com" subject="Current Gas Desk List">1</tf><tf date="2000/10/09 07:00" file="FINDMAIL/HTML_files/1 (17th copy)/25182.txt" id="25182" sender="phillip.allen@enron.com" subject="Consolidated positions Issues To Do list">1</tf><tf date="2000/09/12 04:23" file="FINDMAIL/HTML_files/1 (27th copy)/15199.txt" id="15199" sender="phillip.allen@enron.com" subject="Contact list for mid market">1</tf><tf date="2000/03/13 05:31" file="FINDMAIL/HTML_files/1 (another copy)/5395.txt" id="5395" sender="phillip.allen@enron.com" subject="Priority List">1</tf><tf date="1979/12/31 16:00" file="FINDMAIL/HTML_files/1 (21st copy)/20934.txt" id="20934" sender="phillip.allen@enron.com" subject="systems wish list">1</tf><tf date="2000/10/09 07:16" file="FINDMAIL/HTML_files/1 (4th copy)/6708.txt" id="6708" sender="phillip.allen@enron.com" subject="Consolidated positions Issues To Do list">1</tf><tf date="2000/10/09 07:16" file="FINDMAIL/HTML_files/1 (copy)/10708.txt" id="10708" sender="phillip.allen@enron.com" subject="Consolidated positions Issues To Do list">1</tf><tf date="1979/12/31 16:00" file="FINDMAIL/HTML_files/1 (15th copy)/3271.txt" id="3271" sender="phillip.allen@enron.com" subject="systems wish list">1</tf><tf date="2000/10/09 07:00" file="FINDMAIL/HTML_files/1 (copy)/10432.txt" id="10432" sender="phillip.allen@enron.com" subject="Consolidated positions Issues To Do list">1</tf><tf date="2000/03/13 05:31" file="FINDMAIL/HTML_files/1 (16th copy)/22395.txt" id="22395" sender="phillip.allen@enron.com" subject="Priority List">1</tf><tf date="2000/10/09 07:16" file="FINDMAIL/HTML_files/1 (25th copy)/17708.txt" id="17708" sender="phillip.allen@enron.com" subject="Consolidated positions Issues To Do list">1</tf><tf date="2001/04/04 07:43" file="FINDMAIL/HTML_files/1 (16th copy)/22853.txt" id="22853" sender="phillip.allen@enron.com" subject="Re Answers to List">1</tf><tf date="2000/03/13 05:31" file="FINDMAIL/HTML_files/1 (16th copy)/22851.txt" id="22851" sender="phillip.allen@enron.com" subject="Priority List">1</tf><tf date="2000/10/09 07:00" file="FINDMAIL/HTML_files/1 (26th copy)/7432.txt" id="7432" sender="phillip.allen@enron.com" subject="Consolidated positions Issues To Do list">1</tf><tf date="1979/12/31 16:00" file="FINDMAIL/HTML_files/1 (8th copy)/11934.txt" id="11934" sender="phillip.allen@enron.com" subject="systems wish list">1</tf><tf date="2000/09/12 04:23" file="FINDMAIL/HTML_files/1 (19th copy)/27905.txt" id="27905" sender="phillip.allen@enron.com" subject="Contact list for mid market">1</tf><tf date="2001/04/04 07:43" file="FINDMAIL/HTML_files/1 (18th copy)/26853.txt" id="26853" sender="phillip.allen@enron.com" subject="Re Answers to List">1</tf><tf date="2000/03/13 05:31" file="FINDMAIL/HTML_files/1 (18th copy)/26851.txt" id="26851" sender="phillip.allen@enron.com" subject="Priority List">1</tf><tf date="2001/04/18 11:11" file="FINDMAIL/HTML_files/1 (17th copy)/25512.txt" id="25512" sender="phillip.allen@enron.com" subject="approved trader list">1</tf><tf date="2000/09/12 04:23" file="FINDMAIL/HTML_files/1 (15th copy)/3199.txt" id="3199" sender="phillip.allen@enron.com" subject="Contact list for mid market">1</tf><tf date="1979/12/31 16:00" file="FINDMAIL/HTML_files/1 (11th copy)/2934.txt" id="2934" sender="phillip.allen@enron.com" subject="systems wish list">1</tf><tf date="2000/10/09 07:00" file="FINDMAIL/HTML_files/1 (21st copy)/20432.txt" id="20432" sender="phillip.allen@enron.com" subject="Consolidated positions Issues To Do list">1</tf><tf date="2000/10/09 07:00" file="FINDMAIL/HTML_files/1 (19th copy)/27583.txt" id="27583" sender="phillip.allen@enron.com" subject="Consolidated positions Issues To Do list">1</tf><tf date="2000/10/09 07:00" file="FINDMAIL/HTML_files/1 (12th copy)/18583.txt" id="18583" sender="phillip.allen@enron.com" subject="Consolidated positions Issues To Do list">1</tf><tf date="2000/10/09 07:16" file="FINDMAIL/HTML_files/1 (another copy)/5484.txt" id="5484" sender="phillip.allen@enron.com" subject="Consolidated positions Issues To Do list">1</tf><tf date="2000/03/13 05:31" file="FINDMAIL/HTML_files/1 (23rd copy)/9395.txt" id="9395" sender="phillip.allen@enron.com" subject="Priority List">1</tf><tf date="2000/10/09 07:00" file="FINDMAIL/HTML_files/1 (21st copy)/20182.txt" id="20182" sender="phillip.allen@enron.com" subject="Consolidated positions Issues To Do list">1</tf><tf date="2000/09/12 04:23" file="FINDMAIL/HTML_files/1 (copy)/10988.txt" id="10988" sender="phillip.allen@enron.com" subject="Contact list for mid market">1</tf><tf date="2000/03/13 05:31" file="FINDMAIL/HTML_files/1 (19th copy)/27395.txt" id="27395" sender="phillip.allen@enron.com" subject="Priority List">1</tf><tf date="2001/04/18 11:11" file="FINDMAIL/HTML_files/1 (8th copy)/11512.txt" id="11512" sender="phillip.allen@enron.com" subject="approved trader list">1</tf><tf date="2001/04/18 01:11" file="FINDMAIL/HTML_files/1 (8th copy)/11298.txt" id="11298" sender="phillip.allen@enron.com" subject="approved trader list">1</tf><tf date="1979/12/31 16:00" file="FINDMAIL/HTML_files/1 (24th copy)/14934.txt" id="14934" sender="phillip.allen@enron.com" subject="systems wish list">1</tf><tf date="2000/09/12 04:23" file="FINDMAIL/HTML_files/1 (12th copy)/18905.txt" id="18905" sender="phillip.allen@enron.com" subject="Contact list for mid market">1</tf><tf date="2000/03/13 05:32" file="FINDMAIL/HTML_files/1 (19th copy)/27155.txt" id="27155" sender="phillip.allen@enron.com" subject="Priority List">1</tf><tf date="2000/03/13 05:32" file="FINDMAIL/HTML_files/1 (6th copy)/16155.txt" id="16155" sender="phillip.allen@enron.com" subject="Priority List">1</tf><tf date="1979/12/31 16:00" file="FINDMAIL/HTML_files/1 (12th copy)/18271.txt" id="18271" sender="phillip.allen@enron.com" subject="systems wish list">1</tf><tf date="2000/03/13 05:31" file="FINDMAIL/HTML_files/1 (3rd copy)/19851.txt" id="19851" sender="phillip.allen@enron.com" subject="Priority List">1</tf><tf date="2001/04/18 01:11" file="FINDMAIL/HTML_files/1 (11th copy)/2298.txt" id="2298" sender="phillip.allen@enron.com" subject="approved trader list">1</tf><tf date="2000/09/12 04:23" file="FINDMAIL/HTML_files/1 (12th copy)/18199.txt" id="18199" sender="phillip.allen@enron.com" subject="Contact list for mid market">1</tf><tf date="2000/03/13 05:31" file="FINDMAIL/HTML_files/1 (19th copy)/27851.txt" id="27851" sender="phillip.allen@enron.com" subject="Priority List">1</tf><tf date="2000/10/09 07:16" file="FINDMAIL/HTML_files/1 (14th copy)/13526.txt" id="13526" sender="phillip.allen@enron.com" subject="Consolidated positions Issues To Do list">1</tf><tf date="2000/09/12 04:23" file="FINDMAIL/HTML_files/1 (11th copy)/2199.txt" id="2199" sender="phillip.allen@enron.com" subject="Contact list for mid market">1</tf><tf date="2000/10/09 07:00" file="FINDMAIL/HTML_files/1 (16th copy)/22583.txt" id="22583" sender="phillip.allen@enron.com" subject="Consolidated positions Issues To Do list">1</tf><tf date="2001/04/18 01:11" file="FINDMAIL/HTML_files/1 (12th copy)/18298.txt" id="18298" sender="phillip.allen@enron.com" subject="approved trader list">1</tf><tf date="1979/12/31 16:00" file="FINDMAIL/HTML_files/1 (26th copy)/7934.txt" id="7934" sender="phillip.allen@enron.com" subject="systems wish list">1</tf><tf date="2000/10/09 07:00" file="FINDMAIL/HTML_files/1 (another copy)/5432.txt" id="5432" sender="phillip.allen@enron.com" subject="Consolidated positions Issues To Do list">1</tf><tf date="2000/09/12 04:23" file="FINDMAIL/HTML_files/1 (18th copy)/26988.txt" id="26988" sender="phillip.allen@enron.com" subject="Contact list for mid market">1</tf><tf date="2000/10/09 07:00" file="FINDMAIL/HTML_files/1 (5th copy)/1583.txt" id="1583" sender="phillip.allen@enron.com" subject="Consolidated positions Issues To Do list">1</tf><tf date="2000/03/13 05:32" file="FINDMAIL/HTML_files/1 (26th copy)/7155.txt" id="7155" sender="phillip.allen@enron.com" subject="Priority List">1</tf><tf date="2000/03/13 05:31" file="FINDMAIL/HTML_files/1 (19th copy)/27459.txt" id="27459" sender="phillip.allen@enron.com" subject="Priority List">1</tf><tf date="2001/04/18 11:11" file="FINDMAIL/HTML_files/1 (19th copy)/27512.txt" id="27512" sender="phillip.allen@enron.com" subject="approved trader list">1</tf><tf date="2000/09/12 04:23" file="FINDMAIL/HTML_files/1 (16th copy)/22905.txt" id="22905" sender="phillip.allen@enron.com" subject="Contact list for mid market">1</tf><tf date="2000/10/09 07:00" file="FINDMAIL/HTML_files/1 (8th copy)/11583.txt" id="11583" sender="phillip.allen@enron.com" subject="Consolidated positions Issues To Do list">1</tf><tf date="2000/03/13 05:31" file="FINDMAIL/HTML_files/1 (29th copy)/29395.txt" id="29395" sender="phillip.allen@enron.com" subject="Priority List">1</tf><tf date="1979/12/31 16:00" file="FINDMAIL/HTML_files/1 (29th copy)/29934.txt" id="29934" sender="phillip.allen@enron.com" subject="systems wish list">1</tf><tf date="2000/09/12 04:23" file="FINDMAIL/HTML_files/1 (21st copy)/20988.txt" id="20988" sender="phillip.allen@enron.com" subject="Contact list for mid market">1</tf><tf date="1979/12/31 16:00" file="FINDMAIL/HTML_files/1 (22nd copy)/4271.txt" id="4271" sender="phillip.allen@enron.com" subject="systems wish list">1</tf><tf date="2000/03/13 05:31" file="FINDMAIL/HTML_files/1 (14th copy)/13459.txt" id="13459" sender="phillip.allen@enron.com" subject="Priority List">1</tf><tf date="2000/10/09 07:00" file="FINDMAIL/HTML_files/1 (11th copy)/2583.txt" id="2583" sender="phillip.allen@enron.com" subject="Consolidated positions Issues To Do list">1</tf><tf date="2000/10/09 07:16" file="FINDMAIL/HTML_files/1 (20th copy)/23526.txt" id="23526" sender="phillip.allen@enron.com" subject="Consolidated positions Issues To Do list">1</tf><tf date="2001/04/18 01:11" file="FINDMAIL/HTML_files/1 (26th copy)/7298.txt" id="7298" sender="phillip.allen@enron.com" subject="approved trader list">1</tf><tf date="2001/04/18 01:11" file="FINDMAIL/HTML_files/1 (14th copy)/13298.txt" id="13298" sender="phillip.allen@enron.com" subject="approved trader list">1</tf><tf date="2000/10/09 07:16" file="FINDMAIL/HTML_files/1 (26th copy)/7484.txt" id="7484" sender="phillip.allen@enron.com" subject="Consolidated positions Issues To Do list">1</tf><tf date="2001/04/18 01:11" file="FINDMAIL/HTML_files/1 (25th copy)/17298.txt" id="17298" sender="phillip.allen@enron.com" subject="approved trader list">1</tf><tf date="2000/10/09 07:16" file="FINDMAIL/HTML_files/1 (4th copy)/6526.txt" id="6526" sender="phillip.allen@enron.com" subject="Consolidated positions Issues To Do list">1</tf><tf date="2000/10/09 07:16" file="FINDMAIL/HTML_files/1 (25th copy)/17526.txt" id="17526" sender="phillip.allen@enron.com" subject="Consolidated positions Issues To Do list">1</tf><tf date="2001/04/18 11:11" file="FINDMAIL/HTML_files/1 (7th copy)/21512.txt" id="21512" sender="phillip.allen@enron.com" subject="approved trader list">1</tf><tf date="2000/10/09 07:16" file="FINDMAIL/HTML_files/1 (4th copy)/6484.txt" id="6484" sender="phillip.allen@enron.com" subject="Consolidated positions Issues To Do list">1</tf><tf date="2001/04/04 07:43" file="FINDMAIL/HTML_files/1 (13th copy)/24853.txt" id="24853" sender="phillip.allen@enron.com" subject="Re Answers to List">1</tf><tf date="1979/12/31 16:00" file="FINDMAIL/HTML_files/1 (22nd copy)/4934.txt" id="4934" sender="phillip.allen@enron.com" subject="systems wish list">1</tf><tf date="2000/03/13 05:31" file="FINDMAIL/HTML_files/1 (17th copy)/25851.txt" id="25851" sender="phillip.allen@enron.com" subject="Priority List">1</tf><tf date="2001/04/18 01:11" file="FINDMAIL/HTML_files/1 (4th copy)/6298.txt" id="6298" sender="phillip.allen@enron.com" subject="approved trader list">1</tf><tf date="2000/10/09 07:16" file="FINDMAIL/HTML_files/1 (22nd copy)/4526.txt" id="4526" sender="phillip.allen@enron.com" subject="Consolidated positions Issues To Do list">1</tf><tf date="2000/10/09 07:00" file="FINDMAIL/HTML_files/1 (10th copy)/8583.txt" id="8583" sender="phillip.allen@enron.com" subject="Consolidated positions Issues To Do list">1</tf><tf date="2000/10/09 07:00" file="FINDMAIL/HTML_files/1 (23rd copy)/9432.txt" id="9432" sender="phillip.allen@enron.com" subject="Consolidated positions Issues To Do list">1</tf><tf date="2000/09/12 04:23" file="FINDMAIL/HTML_files/1 (4th copy)/6199.txt" id="6199" sender="phillip.allen@enron.com" subject="Contact list for mid market">1</tf><tf date="2001/04/18 11:11" file="FINDMAIL/HTML_files/1 (11th copy)/2512.txt" id="2512" sender="phillip.allen@enron.com" subject="approved trader list">1</tf><tf date="2001/04/18 11:11" file="FINDMAIL/HTML_files/1 (5th copy)/1512.txt" id="1512" sender="phillip.allen@enron.com" subject="approved trader list">1</tf><tf date="2000/03/13 05:32" file="FINDMAIL/HTML_files/1 (21st copy)/20155.txt" id="20155" sender="phillip.allen@enron.com" subject="Priority List">1</tf><tf date="2001/04/18 01:11" file="FINDMAIL/HTML_files/1 (another copy)/5298.txt" id="5298" sender="phillip.allen@enron.com" subject="approved trader list">1</tf><tf date="2000/03/13 05:31" file="FINDMAIL/HTML_files/1 (7th copy)/21851.txt" id="21851" sender="phillip.allen@enron.com" subject="Priority List">1</tf><tf date="2000/10/09 07:00" file="FINDMAIL/HTML_files/1 (20th copy)/23182.txt" id="23182" sender="phillip.allen@enron.com" subject="Consolidated positions Issues To Do list">1</tf><tf date="2000/10/09 07:00" file="FINDMAIL/HTML_files/1 (23rd copy)/9182.txt" id="9182" sender="phillip.allen@enron.com" subject="Consolidated positions Issues To Do list">1</tf><tf date="2000/03/13 05:31" file="FINDMAIL/HTML_files/1 (15th copy)/3395.txt" id="3395" sender="phillip.allen@enron.com" subject="Priority List">1</tf><tf date="2000/10/09 07:00" file="FINDMAIL/HTML_files/1 (14th copy)/13182.txt" id="13182" sender="phillip.allen@enron.com" subject="Consolidated positions Issues To Do list">1</tf><tf date="2001/04/18 11:11" file="FINDMAIL/HTML_files/1 (18th copy)/26512.txt" id="26512" sender="phillip.allen@enron.com" subject="approved trader list">1</tf><tf date="2000/10/09 07:16" file="FINDMAIL/HTML_files/1 (7th copy)/21708.txt" id="21708" sender="phillip.allen@enron.com" subject="Consolidated positions Issues To Do list">1</tf><tf date="2000/10/09 07:16" file="FINDMAIL/HTML_files/1 (8th copy)/11484.txt" id="11484" sender="phillip.allen@enron.com" subject="Consolidated positions Issues To Do list">1</tf><tf date="2000/09/12 04:23" file="FINDMAIL/HTML_files/1 (6th copy)/16905.txt" id="16905" sender="phillip.allen@enron.com" subject="Contact list for mid market">1</tf><tf date="2000/10/09 07:00" file="FINDMAIL/HTML_files/1 (15th copy)/3432.txt" id="3432" sender="phillip.allen@enron.com" subject="Consolidated positions Issues To Do list">1</tf><tf date="2000/10/09 07:16" file="FINDMAIL/HTML_files/1 (13th copy)/24708.txt" id="24708" sender="phillip.allen@enron.com" subject="Consolidated positions Issues To Do list">1</tf><tf date="2001/03/26 02:03" file="FINDMAIL/HTML_files/1 (copy)/10762.txt" id="10762" sender="phillip.allen@enron.com" subject="Current Gas Desk List">1</tf><tf date="2001/03/26 02:03" file="FINDMAIL/HTML_files/1 (9th copy)/28762.txt" id="28762" sender="phillip.allen@enron.com" subject="Current Gas Desk List">1</tf><tf date="2000/10/09 07:00" file="FINDMAIL/HTML_files/1 (15th copy)/3182.txt" id="3182" sender="phillip.allen@enron.com" subject="Consolidated positions Issues To Do list">1</tf><tf date="2000/03/13 05:31" file="FINDMAIL/HTML_files/1 (21st copy)/20459.txt" id="20459" sender="phillip.allen@enron.com" subject="Priority List">1</tf><tf date="2000/10/09 07:00" file="FINDMAIL/HTML_files/1 (13th copy)/24432.txt" id="24432" sender="phillip.allen@enron.com" subject="Consolidated positions Issues To Do list">1</tf><tf date="2000/10/09 07:16" file="FINDMAIL/HTML_files/1 (copy)/10484.txt" id="10484" sender="phillip.allen@enron.com" subject="Consolidated positions Issues To Do list">1</tf><tf date="2000/10/09 07:16" file="FINDMAIL/HTML_files/1 (3rd copy)/19484.txt" id="19484" sender="phillip.allen@enron.com" subject="Consolidated positions Issues To Do list">1</tf><tf date="2001/04/18 11:11" file="FINDMAIL/HTML_files/1 (6th copy)/16512.txt" id="16512" sender="phillip.allen@enron.com" subject="approved trader list">1</tf><tf date="2000/03/13 05:31" file="FINDMAIL/HTML_files/1 (16th copy)/22459.txt" id="22459" sender="phillip.allen@enron.com" subject="Priority List">1</tf><tf date="2000/09/12 04:23" file="FINDMAIL/HTML_files/1 (24th copy)/14905.txt" id="14905" sender="phillip.allen@enron.com" subject="Contact list for mid market">1</tf><tf date="2001/03/26 02:03" file="FINDMAIL/HTML_files/1 (23rd copy)/9762.txt" id="9762" sender="phillip.allen@enron.com" subject="Current Gas Desk List">1</tf><tf date="2001/04/18 01:11" file="FINDMAIL/HTML_files/1/12298.txt" id="12298" sender="phillip.allen@enron.com" subject="approved trader list">1</tf><tf date="2001/04/18 11:11" file="FINDMAIL/HTML_files/1 (16th copy)/22512.txt" id="22512" sender="phillip.allen@enron.com" subject="approved trader list">1</tf><tf date="2000/10/09 07:16" file="FINDMAIL/HTML_files/1 (14th copy)/13708.txt" id="13708" sender="phillip.allen@enron.com" subject="Consolidated positions Issues To Do list">1</tf><tf date="2000/10/09 07:00" file="FINDMAIL/HTML_files/1 (18th copy)/26583.txt" id="26583" sender="phillip.allen@enron.com" subject="Consolidated positions Issues To Do list">1</tf><tf date="2000/03/13 05:32" file="FINDMAIL/HTML_files/1 (22nd copy)/4155.txt" id="4155" sender="phillip.allen@enron.com" subject="Priority List">1</tf><tf date="2001/04/18 01:11" file="FINDMAIL/HTML_files/1 (23rd copy)/9298.txt" id="9298" sender="phillip.allen@enron.com" subject="approved trader list">1</tf><tf date="2001/04/18 01:11" file="FINDMAIL/HTML_files/1 (21st copy)/20298.txt" id="20298" sender="phillip.allen@enron.com" subject="approved trader list">1</tf><tf date="2000/10/09 07:00" file="FINDMAIL/HTML_files/1 (3rd copy)/19432.txt" id="19432" sender="phillip.allen@enron.com" subject="Consolidated positions Issues To Do list">1</tf><tf date="2000/10/09 07:00" file="FINDMAIL/HTML_files/1 (12th copy)/18432.txt" id="18432" sender="phillip.allen@enron.com" subject="Consolidated positions Issues To Do list">1</tf><tf date="2000/09/12 04:23" file="FINDMAIL/HTML_files/1 (15th copy)/3988.txt" id="3988" sender="phillip.allen@enron.com" subject="Contact list for mid market">1</tf><tf date="2000/09/12 04:23" file="FINDMAIL/HTML_files/1 (16th copy)/22199.txt" id="22199" sender="phillip.allen@enron.com" subject="Contact list for mid market">1</tf><tf date="1979/12/31 16:00" file="FINDMAIL/HTML_files/1 (14th copy)/13271.txt" id="13271" sender="phillip.allen@enron.com" subject="systems wish list">1</tf><tf date="2001/04/04 07:43" file="FINDMAIL/HTML_files/1 (10th copy)/8853.txt" id="8853" sender="phillip.allen@enron.com" subject="Re Answers to List">1</tf><tf date="2000/03/13 05:31" file="FINDMAIL/HTML_files/1 (10th copy)/8851.txt" id="8851" sender="phillip.allen@enron.com" subject="Priority List">1</tf><tf date="2001/03/26 02:03" file="FINDMAIL/HTML_files/1 (28th copy)/762.txt" id="762" sender="phillip.allen@enron.com" subject="Current Gas Desk List">1</tf><tf date="2001/03/26 02:03" file="FINDMAIL/HTML_files/1 (12th copy)/18762.txt" id="18762" sender="phillip.allen@enron.com" subject="Current Gas Desk List">1</tf><tf date="2001/03/26 02:03" file="FINDMAIL/HTML_files/1 (6th copy)/16762.txt" id="16762" sender="phillip.allen@enron.com" subject="Current Gas Desk List">1</tf><tf date="1979/12/31 16:00" file="FINDMAIL/HTML_files/1 (21st copy)/20271.txt" id="20271" sender="phillip.allen@enron.com" subject="systems wish list">1</tf><tf date="2001/04/04 07:43" file="FINDMAIL/HTML_files/1 (3rd copy)/19853.txt" id="19853" sender="phillip.allen@enron.com" subject="Re Answers to List">1</tf><tf date="2000/09/12 04:23" file="FINDMAIL/HTML_files/1 (29th copy)/29199.txt" id="29199" sender="phillip.allen@enron.com" subject="Contact list for mid market">1</tf><tf date="2001/03/26 02:03" file="FINDMAIL/HTML_files/1 (27th copy)/15762.txt" id="15762" sender="phillip.allen@enron.com" subject="Current Gas Desk List">1</tf><tf date="2000/03/13 05:31" file="FINDMAIL/HTML_files/1 (20th copy)/23851.txt" id="23851" sender="phillip.allen@enron.com" subject="Priority List">1</tf><tf date="1979/12/31 16:00" file="FINDMAIL/HTML_files/1 (another copy)/5271.txt" id="5271" sender="phillip.allen@enron.com" subject="systems wish list">1</tf><tf date="2001/04/04 07:43" file="FINDMAIL/HTML_files/1 (20th copy)/23853.txt" id="23853" sender="phillip.allen@enron.com" subject="Re Answers to List">1</tf><tf date="2000/10/09 07:00" file="FINDMAIL/HTML_files/1 (copy)/10182.txt" id="10182" sender="phillip.allen@enron.com" subject="Consolidated positions Issues To Do list">1</tf><tf date="2001/04/04 07:43" file="FINDMAIL/HTML_files/1 (19th copy)/27853.txt" id="27853" sender="phillip.allen@enron.com" subject="Re Answers to List">1</tf><tf date="2000/10/09 07:16" file="FINDMAIL/HTML_files/1 (22nd copy)/4708.txt" id="4708" sender="phillip.allen@enron.com" subject="Consolidated positions Issues To Do list">1</tf><tf date="2001/04/18 01:11" file="FINDMAIL/HTML_files/1 (29th copy)/29298.txt" id="29298" sender="phillip.allen@enron.com" subject="approved trader list">1</tf><tf date="2000/09/12 04:23" file="FINDMAIL/HTML_files/1 (another copy)/5905.txt" id="5905" sender="phillip.allen@enron.com" subject="Contact list for mid market">1</tf><tf date="2001/04/04 07:43" file="FINDMAIL/HTML_files/1 (7th copy)/21853.txt" id="21853" sender="phillip.allen@enron.com" subject="Re Answers to List">1</tf><tf date="2001/03/26 02:03" file="FINDMAIL/HTML_files/1 (15th copy)/3762.txt" id="3762" sender="phillip.allen@enron.com" subject="Current Gas Desk List">1</tf><tf date="2001/04/18 01:11" file="FINDMAIL/HTML_files/1 (17th copy)/25298.txt" id="25298" sender="phillip.allen@enron.com" subject="approved trader list">1</tf><tf date="1979/12/31 16:00" file="FINDMAIL/HTML_files/1 (27th copy)/15934.txt" id="15934" sender="phillip.allen@enron.com" subject="systems wish list">1</tf><tf date="2000/03/13 05:32" file="FINDMAIL/HTML_files/1 (5th copy)/1155.txt" id="1155" sender="phillip.allen@enron.com" subject="Priority List">1</tf><tf date="2000/10/09 07:16" file="FINDMAIL/HTML_files/1 (15th copy)/3484.txt" id="3484" sender="phillip.allen@enron.com" subject="Consolidated positions Issues To Do list">1</tf><tf date="2000/09/12 04:23" file="FINDMAIL/HTML_files/1 (13th copy)/24988.txt" id="24988" sender="phillip.allen@enron.com" subject="Contact list for mid market">1</tf><tf date="2000/03/13 05:31" file="FINDMAIL/HTML_files/1 (4th copy)/6459.txt" id="6459" sender="phillip.allen@enron.com" subject="Priority List">1</tf><tf date="2000/03/13 05:31" file="FINDMAIL/HTML_files/1 (17th copy)/25459.txt" id="25459" sender="phillip.allen@enron.com" subject="Priority List">1</tf><tf date="2001/04/18 11:11" file="FINDMAIL/HTML_files/1 (another copy)/5512.txt" id="5512" sender="phillip.allen@enron.com" subject="approved trader list">1</tf><tf date="2000/03/13 05:31" file="FINDMAIL/HTML_files/1 (25th copy)/17395.txt" id="17395" sender="phillip.allen@enron.com" subject="Priority List">1</tf><tf date="2000/10/09 07:00" file="FINDMAIL/HTML_files/1 (24th copy)/14583.txt" id="14583" sender="phillip.allen@enron.com" subject="Consolidated positions Issues To Do list">1</tf><tf date="2000/10/09 07:16" file="FINDMAIL/HTML_files/1 (19th copy)/27526.txt" id="27526" sender="phillip.allen@enron.com" subject="Consolidated positions Issues To Do list">1</tf><tf date="2000/09/12 04:23" file="FINDMAIL/HTML_files/1 (7th copy)/21988.txt" id="21988" sender="phillip.allen@enron.com" subject="Contact list for mid market">1</tf><tf date="2000/10/09 07:00" file="FINDMAIL/HTML_files/1 (9th copy)/28432.txt" id="28432" sender="phillip.allen@enron.com" subject="Consolidated positions Issues To Do list">1</tf><tf date="2001/04/04 07:43" file="FINDMAIL/HTML_files/1 (25th copy)/17853.txt" id="17853" sender="phillip.allen@enron.com" subject="Re Answers to List">1</tf><tf date="2000/03/13 05:31" file="FINDMAIL/HTML_files/1 (4th copy)/6395.txt" id="6395" sender="phillip.allen@enron.com" subject="Priority List">1</tf><tf date="2000/10/09 07:00" file="FINDMAIL/HTML_files/1 (17th copy)/25583.txt" id="25583" sender="phillip.allen@enron.com" subject="Consolidated positions Issues To Do list">1</tf><tf date="2000/03/13 05:31" file="FINDMAIL/HTML_files/1 (11th copy)/2395.txt" id="2395" sender="phillip.allen@enron.com" subject="Priority List">1</tf><tf date="2000/09/12 04:23" file="FINDMAIL/HTML_files/1 (29th copy)/29905.txt" id="29905" sender="phillip.allen@enron.com" subject="Contact list for mid market">1</tf><tf date="2000/09/12 04:23" file="FINDMAIL/HTML_files/1 (27th copy)/15988.txt" id="15988" sender="phillip.allen@enron.com" subject="Contact list for mid market">1</tf><tf date="2000/03/13 05:31" file="FINDMAIL/HTML_files/1 (13th copy)/24851.txt" id="24851" sender="phillip.allen@enron.com" subject="Priority List">1</tf><tf date="2000/10/09 07:16" file="FINDMAIL/HTML_files/1 (10th copy)/8708.txt" id="8708" sender="phillip.allen@enron.com" subject="Consolidated positions Issues To Do list">1</tf><tf date="2001/04/18 11:11" file="FINDMAIL/HTML_files/1 (29th copy)/29512.txt" id="29512" sender="phillip.allen@enron.com" subject="approved trader list">1</tf><tf date="2000/10/09 07:00" file="FINDMAIL/HTML_files/1 (13th copy)/24182.txt" id="24182" sender="phillip.allen@enron.com" subject="Consolidated positions Issues To Do list">1</tf><tf date="2001/04/04 07:43" file="FINDMAIL/HTML_files/1 (14th copy)/13853.txt" id="13853" sender="phillip.allen@enron.com" subject="Re Answers to List">1</tf><tf date="2000/09/12 04:23" file="FINDMAIL/HTML_files/1 (28th copy)/988.txt" id="988" sender="phillip.allen@enron.com" subject="Contact list for mid market">1</tf><tf date="2000/03/13 05:31" file="FINDMAIL/HTML_files/1 (14th copy)/13851.txt" id="13851" sender="phillip.allen@enron.com" subject="Priority List">1</tf><tf date="2000/10/09 07:00" file="FINDMAIL/HTML_files/1 (7th copy)/21182.txt" id="21182" sender="phillip.allen@enron.com" subject="Consolidated positions Issues To Do list">1</tf><tf date="1979/12/31 16:00" file="FINDMAIL/HTML_files/1 (19th copy)/27934.txt" id="27934" sender="phillip.allen@enron.com" subject="systems wish list">1</tf><tf date="2000/03/13 05:32" file="FINDMAIL/HTML_files/1 (another copy)/5155.txt" id="5155" sender="phillip.allen@enron.com" subject="Priority List">1</tf><tf date="1979/12/31 16:00" file="FINDMAIL/HTML_files/1 (9th copy)/28934.txt" id="28934" sender="phillip.allen@enron.com" subject="systems wish list">1</tf><tf date="2000/03/13 05:31" file="FINDMAIL/HTML_files/1 (23rd copy)/9851.txt" id="9851" sender="phillip.allen@enron.com" subject="Priority List">1</tf><tf date="2000/09/12 04:23" file="FINDMAIL/HTML_files/1 (4th copy)/6905.txt" id="6905" sender="phillip.allen@enron.com" subject="Contact list for mid market">1</tf><tf date="2001/04/04 07:43" file="FINDMAIL/HTML_files/1 (23rd copy)/9853.txt" id="9853" sender="phillip.allen@enron.com" subject="Re Answers to List">1</tf><tf date="2000/10/09 07:00" file="FINDMAIL/HTML_files/1 (27th copy)/15432.txt" id="15432" sender="phillip.allen@enron.com" subject="Consolidated positions Issues To Do list">1</tf><tf date="2000/10/09 07:00" file="FINDMAIL/HTML_files/1/12583.txt" id="12583" sender="phillip.allen@enron.com" subject="Consolidated positions Issues To Do list">1</tf><tf date="2000/10/09 07:16" file="FINDMAIL/HTML_files/1 (19th copy)/27708.txt" id="27708" sender="phillip.allen@enron.com" subject="Consolidated positions Issues To Do list">1</tf><tf date="2001/04/04 07:43" file="FINDMAIL/HTML_files/1/12853.txt" id="12853" sender="phillip.allen@enron.com" subject="Re Answers to List">1</tf><tf date="2000/03/13 05:31" file="FINDMAIL/HTML_files/1 (25th copy)/17851.txt" id="17851" sender="phillip.allen@enron.com" subject="Priority List">1</tf><tf date="2001/03/26 02:03" file="FINDMAIL/HTML_files/1 (another copy)/5762.txt" id="5762" sender="phillip.allen@enron.com" subject="Current Gas Desk List">1</tf><tf date="2000/10/09 07:16" file="FINDMAIL/HTML_files/1 (10th copy)/8526.txt" id="8526" sender="phillip.allen@enron.com" subject="Consolidated positions Issues To Do list">1</tf><tf date="2000/03/13 05:31" file="FINDMAIL/HTML_files/1 (14th copy)/13395.txt" id="13395" sender="phillip.allen@enron.com" subject="Priority List">1</tf><tf date="2001/04/18 11:11" file="FINDMAIL/HTML_files/1 (24th copy)/14512.txt" id="14512" sender="phillip.allen@enron.com" subject="approved trader list">1</tf><tf date="2000/03/13 05:31" file="FINDMAIL/HTML_files/1 (5th copy)/1851.txt" id="1851" sender="phillip.allen@enron.com" subject="Priority List">1</tf><tf date="2001/04/18 11:11" file="FINDMAIL/HTML_files/1 (4th copy)/6512.txt" id="6512" sender="phillip.allen@enron.com" subject="approved trader list">1</tf><tf date="2000/03/13 05:31" file="FINDMAIL/HTML_files/1/12395.txt" id="12395" sender="phillip.allen@enron.com" subject="Priority List">1</tf><tf date="2000/09/12 04:23" file="FINDMAIL/HTML_files/1 (17th copy)/25199.txt" id="25199" sender="phillip.allen@enron.com" subject="Contact list for mid market">1</tf><tf date="2000/10/09 07:16" file="FINDMAIL/HTML_files/1 (5th copy)/1526.txt" id="1526" sender="phillip.allen@enron.com" subject="Consolidated positions Issues To Do list">1</tf><tf date="2000/03/13 05:31" file="FINDMAIL/HTML_files/1 (21st copy)/20851.txt" id="20851" sender="phillip.allen@enron.com" subject="Priority List">1</tf><tf date="2001/04/04 07:43" file="FINDMAIL/HTML_files/1 (21st copy)/20853.txt" id="20853" sender="phillip.allen@enron.com" subject="Re Answers to List">1</tf><tf date="2000/03/13 05:32" file="FINDMAIL/HTML_files/1/12155.txt" id="12155" sender="phillip.allen@enron.com" subject="Priority List">1</tf><tf date="2000/03/13 05:31" file="FINDMAIL/HTML_files/1 (5th copy)/1395.txt" id="1395" sender="phillip.allen@enron.com" subject="Priority List">1</tf><tf date="2000/09/12 04:23" file="FINDMAIL/HTML_files/1 (3rd copy)/19199.txt" id="19199" sender="phillip.allen@enron.com" subject="Contact list for mid market">1</tf><tf date="2000/10/09 07:16" file="FINDMAIL/HTML_files/1 (20th copy)/23708.txt" id="23708" sender="phillip.allen@enron.com" subject="Consolidated positions Issues To Do list">1</tf><tf date="1979/12/31 16:00" file="FINDMAIL/HTML_files/1 (5th copy)/1934.txt" id="1934" sender="phillip.allen@enron.com" subject="systems wish list">1</tf><tf date="2000/03/13 05:31" file="FINDMAIL/HTML_files/1 (10th copy)/8459.txt" id="8459" sender="phillip.allen@enron.com" subject="Priority List">1</tf><tf date="2000/03/13 05:31" file="FINDMAIL/HTML_files/1 (28th copy)/851.txt" id="851" sender="phillip.allen@enron.com" subject="Priority List">1</tf><tf date="1979/12/31 16:00" file="FINDMAIL/HTML_files/1 (26th copy)/7271.txt" id="7271" sender="phillip.allen@enron.com" subject="systems wish list">1</tf><tf date="2000/09/12 04:23" file="FINDMAIL/HTML_files/1 (14th copy)/13988.txt" id="13988" sender="phillip.allen@enron.com" subject="Contact list for mid market">1</tf><tf date="2001/04/18 01:11" file="FINDMAIL/HTML_files/1 (22nd copy)/4298.txt" id="4298" sender="phillip.allen@enron.com" subject="approved trader list">1</tf><tf date="2000/09/12 04:23" file="FINDMAIL/HTML_files/1 (19th copy)/27199.txt" id="27199" sender="phillip.allen@enron.com" subject="Contact list for mid market">1</tf><tf date="2000/09/12 04:23" file="FINDMAIL/HTML_files/1 (16th copy)/22988.txt" id="22988" sender="phillip.allen@enron.com" subject="Contact list for mid market">1</tf><tf date="2000/03/13 05:31" file="FINDMAIL/HTML_files/1/12459.txt" id="12459" sender="phillip.allen@enron.com" subject="Priority List">1</tf><tf date="2001/04/18 11:11" file="FINDMAIL/HTML_files/1/12512.txt" id="12512" sender="phillip.allen@enron.com" subject="approved trader list">1</tf><tf date="2000/10/09 07:00" file="FINDMAIL/HTML_files/1 (21st copy)/20583.txt" id="20583" sender="phillip.allen@enron.com" subject="Consolidated positions Issues To Do list">1</tf><tf date="2000/10/09 07:00" file="FINDMAIL/HTML_files/1 (29th copy)/29182.txt" id="29182" sender="phillip.allen@enron.com" subject="Consolidated positions Issues To Do list">1</tf><tf date="2001/03/26 02:03" file="FINDMAIL/HTML_files/1 (13th copy)/24762.txt" id="24762" sender="phillip.allen@enron.com" subject="Current Gas Desk List">1</tf><tf date="2000/03/13 05:32" file="FINDMAIL/HTML_files/1 (9th copy)/28155.txt" id="28155" sender="phillip.allen@enron.com" subject="Priority List">1</tf><tf date="2000/09/12 04:23" file="FINDMAIL/HTML_files/1 (18th copy)/26905.txt" id="26905" sender="phillip.allen@enron.com" subject="Contact list for mid market">1</tf><tf date="2000/03/13 05:31" file="FINDMAIL/HTML_files/1 (15th copy)/3459.txt" id="3459" sender="phillip.allen@enron.com" subject="Priority List">1</tf><tf date="2000/10/09 07:16" file="FINDMAIL/HTML_files/1 (6th copy)/16526.txt" id="16526" sender="phillip.allen@enron.com" subject="Consolidated positions Issues To Do list">1</tf><tf date="2000/03/13 05:31" file="FINDMAIL/HTML_files/1 (4th copy)/6851.txt" id="6851" sender="phillip.allen@enron.com" subject="Priority List">1</tf><tf date="2001/04/04 07:43" file="FINDMAIL/HTML_files/1 (copy)/10853.txt" id="10853" sender="phillip.allen@enron.com" subject="Re Answers to List">1</tf><tf date="2001/04/04 07:43" file="FINDMAIL/HTML_files/1 (4th copy)/6853.txt" id="6853" sender="phillip.allen@enron.com" subject="Re Answers to List">1</tf><tf date="2000/03/13 05:31" file="FINDMAIL/HTML_files/1 (copy)/10851.txt" id="10851" sender="phillip.allen@enron.com" subject="Priority List">1</tf><tf date="2000/10/09 07:16" file="FINDMAIL/HTML_files/1 (29th copy)/29708.txt" id="29708" sender="phillip.allen@enron.com" subject="Consolidated positions Issues To Do list">1</tf><tf date="2001/04/18 01:11" file="FINDMAIL/HTML_files/1 (3rd copy)/19298.txt" id="19298" sender="phillip.allen@enron.com" subject="approved trader list">1</tf><tf date="2001/03/26 02:03" file="FINDMAIL/HTML_files/1 (4th copy)/6762.txt" id="6762" sender="phillip.allen@enron.com" subject="Current Gas Desk List">1</tf><tf date="2000/09/12 04:23" file="FINDMAIL/HTML_files/1 (5th copy)/1988.txt" id="1988" sender="phillip.allen@enron.com" subject="Contact list for mid market">1</tf><tf date="2001/03/26 02:03" file="FINDMAIL/HTML_files/1 (3rd copy)/19762.txt" id="19762" sender="phillip.allen@enron.com" subject="Current Gas Desk List">1</tf><tf date="2000/03/13 05:31" file="FINDMAIL/HTML_files/1 (13th copy)/24459.txt" id="24459" sender="phillip.allen@enron.com" subject="Priority List">1</tf><tf date="2000/03/13 05:32" file="FINDMAIL/HTML_files/1 (27th copy)/15155.txt" id="15155" sender="phillip.allen@enron.com" subject="Priority List">1</tf><tf date="2000/10/09 07:16" file="FINDMAIL/HTML_files/1 (29th copy)/29484.txt" id="29484" sender="phillip.allen@enron.com" subject="Consolidated positions Issues To Do list">1</tf><tf date="2000/10/09 07:00" file="FINDMAIL/HTML_files/1 (6th copy)/16182.txt" id="16182" sender="phillip.allen@enron.com" subject="Consolidated positions Issues To Do list">1</tf><tf date="2000/09/12 04:23" file="FINDMAIL/HTML_files/1 (9th copy)/28199.txt" id="28199" sender="phillip.allen@enron.com" subject="Contact list for mid market">1</tf><tf date="2001/04/18 11:11" file="FINDMAIL/HTML_files/1 (14th copy)/13512.txt" id="13512" sender="phillip.allen@enron.com" subject="approved trader list">1</tf><tf date="2000/10/09 07:16" file="FINDMAIL/HTML_files/1 (24th copy)/14708.txt" id="14708" sender="phillip.allen@enron.com" subject="Consolidated positions Issues To Do list">1</tf><tf date="2000/10/09 07:00" file="FINDMAIL/HTML_files/1 (5th copy)/1182.txt" id="1182" sender="phillip.allen@enron.com" subject="Consolidated positions Issues To Do list">1</tf><tf date="2000/10/09 07:00" file="FINDMAIL/HTML_files/1 (8th copy)/11432.txt" id="11432" sender="phillip.allen@enron.com" subject="Consolidated positions Issues To Do list">1</tf><tf date="2000/10/09 07:00" file="FINDMAIL/HTML_files/1 (3rd copy)/19583.txt" id="19583" sender="phillip.allen@enron.com" subject="Consolidated positions Issues To Do list">1</tf><tf date="2000/03/13 05:32" file="FINDMAIL/HTML_files/1 (28th copy)/155.txt" id="155" sender="phillip.allen@enron.com" subject="Priority List">1</tf><tf date="2000/03/13 05:31" file="FINDMAIL/HTML_files/1 (23rd copy)/9459.txt" id="9459" sender="phillip.allen@enron.com" subject="Priority List">1</tf><tf date="2000/10/09 07:00" file="FINDMAIL/HTML_files/1 (11th copy)/2432.txt" id="2432" sender="phillip.allen@enron.com" subject="Consolidated positions Issues To Do list">1</tf><tf date="2000/03/13 05:31" file="FINDMAIL/HTML_files/1 (25th copy)/17459.txt" id="17459" sender="phillip.allen@enron.com" subject="Priority List">1</tf><tf date="2000/03/13 05:31" file="FINDMAIL/HTML_files/1 (6th copy)/16459.txt" id="16459" sender="phillip.allen@enron.com" subject="Priority List">1</tf><tf date="2000/03/13 05:31" file="FINDMAIL/HTML_files/1/12851.txt" id="12851" sender="phillip.allen@enron.com" subject="Priority List">1</tf><tf date="2000/09/12 04:23" file="FINDMAIL/HTML_files/1 (6th copy)/16988.txt" id="16988" sender="phillip.allen@enron.com" subject="Contact list for mid market">1</tf><tf date="2000/10/09 07:16" file="FINDMAIL/HTML_files/1 (another copy)/5526.txt" id="5526" sender="phillip.allen@enron.com" subject="Consolidated positions Issues To Do list">1</tf><tf date="2001/04/18 11:11" file="FINDMAIL/HTML_files/1 (25th copy)/17512.txt" id="17512" sender="phillip.allen@enron.com" subject="approved trader list">1</tf><tf date="2000/03/13 05:31" file="FINDMAIL/HTML_files/1 (22nd copy)/4459.txt" id="4459" sender="phillip.allen@enron.com" subject="Priority List">1</tf><tf date="2000/10/09 07:00" file="FINDMAIL/HTML_files/1 (26th copy)/7583.txt" id="7583" sender="phillip.allen@enron.com" subject="Consolidated positions Issues To Do list">1</tf><tf date="1979/12/31 16:00" file="FINDMAIL/HTML_files/1 (10th copy)/8271.txt" id="8271" sender="phillip.allen@enron.com" subject="systems wish list">1</tf><tf date="2000/10/09 07:00" file="FINDMAIL/HTML_files/1 (14th copy)/13583.txt" id="13583" sender="phillip.allen@enron.com" subject="Consolidated positions Issues To Do list">1</tf><tf date="2001/04/18 11:11" file="FINDMAIL/HTML_files/1 (22nd copy)/4512.txt" id="4512" sender="phillip.allen@enron.com" subject="approved trader list">1</tf><tf date="1979/12/31 16:00" file="FINDMAIL/HTML_files/1 (9th copy)/28271.txt" id="28271" sender="phillip.allen@enron.com" subject="systems wish list">1</tf><tf date="2001/03/26 02:03" file="FINDMAIL/HTML_files/1 (18th copy)/26762.txt" id="26762" sender="phillip.allen@enron.com" subject="Current Gas Desk List">1</tf><tf date="2001/04/18 01:11" file="FINDMAIL/HTML_files/1 (5th copy)/1298.txt" id="1298" sender="phillip.allen@enron.com" subject="approved trader list">1</tf><tf date="2001/03/26 02:03" file="FINDMAIL/HTML_files/1 (17th copy)/25762.txt" id="25762" sender="phillip.allen@enron.com" subject="Current Gas Desk List">1</tf><tf date="2000/10/09 07:00" file="FINDMAIL/HTML_files/1 (4th copy)/6182.txt" id="6182" sender="phillip.allen@enron.com" subject="Consolidated positions Issues To Do list">1</tf><tf date="2000/09/12 04:23" file="FINDMAIL/HTML_files/1 (25th copy)/17199.txt" id="17199" sender="phillip.allen@enron.com" subject="Contact list for mid market">1</tf><tf date="2000/03/13 05:31" file="FINDMAIL/HTML_files/1 (10th copy)/8395.txt" id="8395" sender="phillip.allen@enron.com" subject="Priority List">1</tf><tf date="2001/04/18 01:11" file="FINDMAIL/HTML_files/1 (9th copy)/28298.txt" id="28298" sender="phillip.allen@enron.com" subject="approved trader list">1</tf><tf date="1979/12/31 16:00" file="FINDMAIL/HTML_files/1 (27th copy)/15271.txt" id="15271" sender="phillip.allen@enron.com" subject="systems wish list">1</tf><tf date="2000/10/09 07:00" file="FINDMAIL/HTML_files/1 (20th copy)/23583.txt" id="23583" sender="phillip.allen@enron.com" subject="Consolidated positions Issues To Do list">1</tf><tf date="2000/09/12 04:23" file="FINDMAIL/HTML_files/1 (20th copy)/23199.txt" id="23199" sender="phillip.allen@enron.com" subject="Contact list for mid market">1</tf><tf date="2000/09/12 04:23" file="FINDMAIL/HTML_files/1 (23rd copy)/9199.txt" id="9199" sender="phillip.allen@enron.com" subject="Contact list for mid market">1</tf><tf date="2000/10/09 07:00" file="FINDMAIL/HTML_files/1 (27th copy)/15182.txt" id="15182" sender="phillip.allen@enron.com" subject="Consolidated positions Issues To Do list">1</tf><tf date="2000/10/09 07:16" file="FINDMAIL/HTML_files/1 (28th copy)/484.txt" id="484" sender="phillip.allen@enron.com" subject="Consolidated positions Issues To Do list">1</tf><tf date="2000/03/13 05:31" file="FINDMAIL/HTML_files/1 (6th copy)/16851.txt" id="16851" sender="phillip.allen@enron.com" subject="Priority List">1</tf><tf date="2001/04/04 07:43" file="FINDMAIL/HTML_files/1 (6th copy)/16853.txt" id="16853" sender="phillip.allen@enron.com" subject="Re Answers to List">1</tf><tf date="2000/10/09 07:00" file="FINDMAIL/HTML_files/1 (20th copy)/23432.txt" id="23432" sender="phillip.allen@enron.com" subject="Consolidated positions Issues To Do list">1</tf><tf date="2000/03/13 05:31" file="FINDMAIL/HTML_files/1 (22nd copy)/4395.txt" id="4395" sender="phillip.allen@enron.com" subject="Priority List">1</tf><tf date="2000/10/09 07:00" file="FINDMAIL/HTML_files/1 (25th copy)/17583.txt" id="17583" sender="phillip.allen@enron.com" subject="Consolidated positions Issues To Do list">1</tf><tf date="2000/03/13 05:31" file="FINDMAIL/HTML_files/1 (7th copy)/21395.txt" id="21395" sender="phillip.allen@enron.com" subject="Priority List">1</tf><tf date="2000/10/09 07:16" file="FINDMAIL/HTML_files/1 (10th copy)/8484.txt" id="8484" sender="phillip.allen@enron.com" subject="Consolidated positions Issues To Do list">1</tf><tf date="2000/10/09 07:00" file="FINDMAIL/HTML_files/1 (22nd copy)/4583.txt" id="4583" sender="phillip.allen@enron.com" subject="Consolidated positions Issues To Do list">1</tf><tf date="2001/04/18 11:11" file="FINDMAIL/HTML_files/1 (23rd copy)/9512.txt" id="9512" sender="phillip.allen@enron.com" subject="approved trader list">1</tf><tf date="1979/12/31 16:00" file="FINDMAIL/HTML_files/1 (17th copy)/25934.txt" id="25934" sender="phillip.allen@enron.com" subject="systems wish list">1</tf><tf date="2001/04/04 07:43" file="FINDMAIL/HTML_files/1 (22nd copy)/4853.txt" id="4853" sender="phillip.allen@enron.com" subject="Re Answers to List">1</tf><tf date="2000/03/13 05:31" file="FINDMAIL/HTML_files/1 (22nd copy)/4851.txt" id="4851" sender="phillip.allen@enron.com" subject="Priority List">1</tf></email>