<email><tf date="2001/02/02 06:59" file="FINDMAIL/HTML_files/1 (16th copy)/22566.txt" id="22566" sender="phillip.allen@enron.com" subject="No Subject">1</tf><tf date="2001/02/02 06:59" file="FINDMAIL/HTML_files/1 (10th copy)/8566.txt" id="8566" sender="phillip.allen@enron.com" subject="No Subject">1</tf><tf date="2001/02/02 06:59" file="FINDMAIL/HTML_files/1 (9th copy)/28566.txt" id="28566" sender="phillip.allen@enron.com" subject="No Subject">1</tf><tf date="2001/02/02 06:59" file="FINDMAIL/HTML_files/1 (17th copy)/25566.txt" id="25566" sender="phillip.allen@enron.com" subject="No Subject">1</tf><tf date="2001/02/02 06:59" file="FINDMAIL/HTML_files/1 (21st copy)/20566.txt" id="20566" sender="phillip.allen@enron.com" subject="No Subject">1</tf><tf date="2001/02/02 06:59" file="FINDMAIL/HTML_files/1 (6th copy)/16566.txt" id="16566" sender="phillip.allen@enron.com" subject="No Subject">1</tf><tf date="2001/02/02 06:59" file="FINDMAIL/HTML_files/1 (8th copy)/11566.txt" id="11566" sender="phillip.allen@enron.com" subject="No Subject">1</tf><tf date="2001/02/02 06:59" file="FINDMAIL/HTML_files/1 (14th copy)/13566.txt" id="13566" sender="phillip.allen@enron.com" subject="No Subject">1</tf><tf date="2001/02/02 06:59" file="FINDMAIL/HTML_files/1 (29th copy)/29566.txt" id="29566" sender="phillip.allen@enron.com" subject="No Subject">1</tf><tf date="2001/02/02 06:59" file="FINDMAIL/HTML_files/1 (another copy)/5566.txt" id="5566" sender="phillip.allen@enron.com" subject="No Subject">1</tf><tf date="2001/02/02 06:59" file="FINDMAIL/HTML_files/1 (11th copy)/2566.txt" id="2566" sender="phillip.allen@enron.com" subject="No Subject">1</tf><tf date="2001/02/02 06:59" file="FINDMAIL/HTML_files/1/12566.txt" id="12566" sender="phillip.allen@enron.com" subject="No Subject">1</tf><tf date="2001/02/02 06:59" file="FINDMAIL/HTML_files/1 (23rd copy)/9566.txt" id="9566" sender="phillip.allen@enron.com" subject="No Subject">1</tf><tf date="2001/02/02 06:59" file="FINDMAIL/HTML_files/1 (5th copy)/1566.txt" id="1566" sender="phillip.allen@enron.com" subject="No Subject">1</tf><tf date="2001/02/02 06:59" file="FINDMAIL/HTML_files/1 (25th copy)/17566.txt" id="17566" sender="phillip.allen@enron.com" subject="No Subject">1</tf><tf date="2001/02/02 06:59" file="FINDMAIL/HTML_files/1 (12th copy)/18566.txt" id="18566" sender="phillip.allen@enron.com" subject="No Subject">1</tf><tf date="2001/02/02 06:59" file="FINDMAIL/HTML_files/1 (28th copy)/566.txt" id="566" sender="phillip.allen@enron.com" subject="No Subject">1</tf><tf date="2001/02/02 06:59" file="FINDMAIL/HTML_files/1 (24th copy)/14566.txt" id="14566" sender="phillip.allen@enron.com" subject="No Subject">1</tf><tf date="2001/02/02 06:59" file="FINDMAIL/HTML_files/1 (22nd copy)/4566.txt" id="4566" sender="phillip.allen@enron.com" subject="No Subject">1</tf><tf date="2001/02/02 06:59" file="FINDMAIL/HTML_files/1 (27th copy)/15566.txt" id="15566" sender="phillip.allen@enron.com" subject="No Subject">1</tf><tf date="2001/02/02 06:59" file="FINDMAIL/HTML_files/1 (20th copy)/23566.txt" id="23566" sender="phillip.allen@enron.com" subject="No Subject">1</tf><tf date="2001/02/02 06:59" file="FINDMAIL/HTML_files/1 (13th copy)/24566.txt" id="24566" sender="phillip.allen@enron.com" subject="No Subject">1</tf><tf date="2001/02/02 06:59" file="FINDMAIL/HTML_files/1 (26th copy)/7566.txt" id="7566" sender="phillip.allen@enron.com" subject="No Subject">1</tf><tf date="2001/02/02 06:59" file="FINDMAIL/HTML_files/1 (15th copy)/3566.txt" id="3566" sender="phillip.allen@enron.com" subject="No Subject">1</tf><tf date="2001/02/02 06:59" file="FINDMAIL/HTML_files/1 (7th copy)/21566.txt" id="21566" sender="phillip.allen@enron.com" subject="No Subject">1</tf><tf date="2001/02/02 06:59" file="FINDMAIL/HTML_files/1 (18th copy)/26566.txt" id="26566" sender="phillip.allen@enron.com" subject="No Subject">1</tf><tf date="2001/02/02 06:59" file="FINDMAIL/HTML_files/1 (4th copy)/6566.txt" id="6566" sender="phillip.allen@enron.com" subject="No Subject">1</tf><tf date="2001/02/02 06:59" file="FINDMAIL/HTML_files/1 (19th copy)/27566.txt" id="27566" sender="phillip.allen@enron.com" subject="No Subject">1</tf><tf date="2001/02/02 06:59" file="FINDMAIL/HTML_files/1 (3rd copy)/19566.txt" id="19566" sender="phillip.allen@enron.com" subject="No Subject">1</tf><tf date="2001/02/02 06:59" file="FINDMAIL/HTML_files/1 (copy)/10566.txt" id="10566" sender="phillip.allen@enron.com" subject="No Subject">1</tf></email>