<email><tf date="2001/03/05 01:38" file="FINDMAIL/HTML_files/1 (17th copy)/25153.txt" id="25153" sender="phillip.allen@enron.com" subject="Re Producer Services">1</tf><tf date="2001/03/05 01:38" file="FINDMAIL/HTML_files/1 (28th copy)/153.txt" id="153" sender="phillip.allen@enron.com" subject="Re Producer Services">1</tf><tf date="2001/03/05 01:38" file="FINDMAIL/HTML_files/1 (another copy)/5153.txt" id="5153" sender="phillip.allen@enron.com" subject="Re Producer Services">1</tf><tf date="2001/03/05 01:38" file="FINDMAIL/HTML_files/1 (10th copy)/8153.txt" id="8153" sender="phillip.allen@enron.com" subject="Re Producer Services">1</tf><tf date="2001/03/05 01:38" file="FINDMAIL/HTML_files/1 (16th copy)/22153.txt" id="22153" sender="phillip.allen@enron.com" subject="Re Producer Services">1</tf><tf date="2001/03/05 01:38" file="FINDMAIL/HTML_files/1 (12th copy)/18153.txt" id="18153" sender="phillip.allen@enron.com" subject="Re Producer Services">1</tf><tf date="2001/03/05 01:38" file="FINDMAIL/HTML_files/1 (24th copy)/14153.txt" id="14153" sender="phillip.allen@enron.com" subject="Re Producer Services">1</tf><tf date="2001/03/05 01:38" file="FINDMAIL/HTML_files/1 (18th copy)/26153.txt" id="26153" sender="phillip.allen@enron.com" subject="Re Producer Services">1</tf><tf date="2001/03/05 01:38" file="FINDMAIL/HTML_files/1 (8th copy)/11153.txt" id="11153" sender="phillip.allen@enron.com" subject="Re Producer Services">1</tf><tf date="2001/03/05 01:38" file="FINDMAIL/HTML_files/1 (26th copy)/7153.txt" id="7153" sender="phillip.allen@enron.com" subject="Re Producer Services">1</tf><tf date="2001/03/05 01:38" file="FINDMAIL/HTML_files/1 (29th copy)/29153.txt" id="29153" sender="phillip.allen@enron.com" subject="Re Producer Services">1</tf><tf date="2001/03/05 01:38" file="FINDMAIL/HTML_files/1 (11th copy)/2153.txt" id="2153" sender="phillip.allen@enron.com" subject="Re Producer Services">1</tf><tf date="2001/03/05 01:38" file="FINDMAIL/HTML_files/1 (20th copy)/23153.txt" id="23153" sender="phillip.allen@enron.com" subject="Re Producer Services">1</tf><tf date="2001/03/05 01:38" file="FINDMAIL/HTML_files/1 (15th copy)/3153.txt" id="3153" sender="phillip.allen@enron.com" subject="Re Producer Services">1</tf><tf date="2001/03/05 01:38" file="FINDMAIL/HTML_files/1 (3rd copy)/19153.txt" id="19153" sender="phillip.allen@enron.com" subject="Re Producer Services">1</tf><tf date="2001/03/05 01:38" file="FINDMAIL/HTML_files/1/12153.txt" id="12153" sender="phillip.allen@enron.com" subject="Re Producer Services">1</tf><tf date="2001/03/05 01:38" file="FINDMAIL/HTML_files/1 (copy)/10153.txt" id="10153" sender="phillip.allen@enron.com" subject="Re Producer Services">1</tf><tf date="2001/03/05 01:38" file="FINDMAIL/HTML_files/1 (27th copy)/15153.txt" id="15153" sender="phillip.allen@enron.com" subject="Re Producer Services">1</tf><tf date="2001/03/05 01:38" file="FINDMAIL/HTML_files/1 (23rd copy)/9153.txt" id="9153" sender="phillip.allen@enron.com" subject="Re Producer Services">1</tf><tf date="2001/03/05 01:38" file="FINDMAIL/HTML_files/1 (5th copy)/1153.txt" id="1153" sender="phillip.allen@enron.com" subject="Re Producer Services">1</tf><tf date="2001/03/05 01:38" file="FINDMAIL/HTML_files/1 (25th copy)/17153.txt" id="17153" sender="phillip.allen@enron.com" subject="Re Producer Services">1</tf><tf date="2001/03/05 01:38" file="FINDMAIL/HTML_files/1 (4th copy)/6153.txt" id="6153" sender="phillip.allen@enron.com" subject="Re Producer Services">1</tf><tf date="2001/03/05 01:38" file="FINDMAIL/HTML_files/1 (7th copy)/21153.txt" id="21153" sender="phillip.allen@enron.com" subject="Re Producer Services">1</tf><tf date="2001/03/05 01:38" file="FINDMAIL/HTML_files/1 (22nd copy)/4153.txt" id="4153" sender="phillip.allen@enron.com" subject="Re Producer Services">1</tf><tf date="2001/03/05 01:38" file="FINDMAIL/HTML_files/1 (14th copy)/13153.txt" id="13153" sender="phillip.allen@enron.com" subject="Re Producer Services">1</tf><tf date="2001/03/05 01:38" file="FINDMAIL/HTML_files/1 (13th copy)/24153.txt" id="24153" sender="phillip.allen@enron.com" subject="Re Producer Services">1</tf><tf date="2001/03/05 01:38" file="FINDMAIL/HTML_files/1 (21st copy)/20153.txt" id="20153" sender="phillip.allen@enron.com" subject="Re Producer Services">1</tf><tf date="2001/03/05 01:38" file="FINDMAIL/HTML_files/1 (9th copy)/28153.txt" id="28153" sender="phillip.allen@enron.com" subject="Re Producer Services">1</tf><tf date="2001/03/05 01:38" file="FINDMAIL/HTML_files/1 (6th copy)/16153.txt" id="16153" sender="phillip.allen@enron.com" subject="Re Producer Services">1</tf><tf date="2001/03/05 01:38" file="FINDMAIL/HTML_files/1 (19th copy)/27153.txt" id="27153" sender="phillip.allen@enron.com" subject="Re Producer Services">1</tf></email>